package com.google.android.gms.internal;

import android.os.Binder;
import android.os.IBinder;
import android.os.IInterface;
import android.os.Parcel;
import android.os.Parcelable.Creator;
import android.os.RemoteException;
import com.google.android.gms.common.data.d;
import com.google.android.gms.common.data.e;
import com.google.android.gms.games.multiplayer.realtime.RealTimeMessage;

public abstract interface ay
  extends IInterface
{
  public abstract void B(int paramInt)
    throws RemoteException;
  
  public abstract void C(int paramInt)
    throws RemoteException;
  
  public abstract void D(int paramInt)
    throws RemoteException;
  
  public abstract void E(int paramInt)
    throws RemoteException;
  
  public abstract void a(int paramInt1, int paramInt2, String paramString)
    throws RemoteException;
  
  public abstract void a(int paramInt, String paramString)
    throws RemoteException;
  
  public abstract void a(int paramInt, String paramString, boolean paramBoolean)
    throws RemoteException;
  
  public abstract void a(d paramd1, d paramd2)
    throws RemoteException;
  
  public abstract void a(d paramd, String[] paramArrayOfString)
    throws RemoteException;
  
  public abstract void b(d paramd)
    throws RemoteException;
  
  public abstract void b(d paramd, String[] paramArrayOfString)
    throws RemoteException;
  
  public abstract void c(d paramd)
    throws RemoteException;
  
  public abstract void c(d paramd, String[] paramArrayOfString)
    throws RemoteException;
  
  public abstract void d(d paramd)
    throws RemoteException;
  
  public abstract void d(d paramd, String[] paramArrayOfString)
    throws RemoteException;
  
  public abstract void e(d paramd)
    throws RemoteException;
  
  public abstract void e(d paramd, String[] paramArrayOfString)
    throws RemoteException;
  
  public abstract void f(d paramd)
    throws RemoteException;
  
  public abstract void f(d paramd, String[] paramArrayOfString)
    throws RemoteException;
  
  public abstract void g(d paramd)
    throws RemoteException;
  
  public abstract void h(d paramd)
    throws RemoteException;
  
  public abstract void i(d paramd)
    throws RemoteException;
  
  public abstract void j(d paramd)
    throws RemoteException;
  
  public abstract void k(d paramd)
    throws RemoteException;
  
  public abstract void l(d paramd)
    throws RemoteException;
  
  public abstract void m(d paramd)
    throws RemoteException;
  
  public abstract void n(d paramd)
    throws RemoteException;
  
  public abstract void o(d paramd)
    throws RemoteException;
  
  public abstract void onAchievementUpdated(int paramInt, String paramString)
    throws RemoteException;
  
  public abstract void onLeftRoom(int paramInt, String paramString)
    throws RemoteException;
  
  public abstract void onP2PConnected(String paramString)
    throws RemoteException;
  
  public abstract void onP2PDisconnected(String paramString)
    throws RemoteException;
  
  public abstract void onRealTimeMessageReceived(RealTimeMessage paramRealTimeMessage)
    throws RemoteException;
  
  public abstract void onSignOutComplete()
    throws RemoteException;
  
  public abstract void p(d paramd)
    throws RemoteException;
  
  public abstract void q(d paramd)
    throws RemoteException;
  
  public abstract void r(d paramd)
    throws RemoteException;
  
  public abstract void s(d paramd)
    throws RemoteException;
  
  public abstract void t(d paramd)
    throws RemoteException;
  
  public abstract void u(d paramd)
    throws RemoteException;
  
  public abstract void v(d paramd)
    throws RemoteException;
  
  public abstract void w(d paramd)
    throws RemoteException;
  
  public static abstract class a
    extends Binder
    implements ay
  {
    public a()
    {
      attachInterface(this, "com.google.android.gms.games.internal.IGamesCallbacks");
    }
    
    public static ay n(IBinder paramIBinder)
    {
      if (paramIBinder == null) {
        return null;
      }
      IInterface localIInterface = paramIBinder.queryLocalInterface("com.google.android.gms.games.internal.IGamesCallbacks");
      if ((localIInterface != null) && ((localIInterface instanceof ay))) {
        return (ay)localIInterface;
      }
      return new a(paramIBinder);
    }
    
    public IBinder asBinder()
    {
      return this;
    }
    
    public boolean onTransact(int paramInt1, Parcel paramParcel1, Parcel paramParcel2, int paramInt2)
      throws RemoteException
    {
      switch (paramInt1)
      {
      default: 
        return super.onTransact(paramInt1, paramParcel1, paramParcel2, paramInt2);
      case 1598968902: 
        paramParcel2.writeString("com.google.android.gms.games.internal.IGamesCallbacks");
        return true;
      case 5001: 
        paramParcel1.enforceInterface("com.google.android.gms.games.internal.IGamesCallbacks");
        a(paramParcel1.readInt(), paramParcel1.readString());
        paramParcel2.writeNoException();
        return true;
      case 5002: 
        paramParcel1.enforceInterface("com.google.android.gms.games.internal.IGamesCallbacks");
        int i26 = paramParcel1.readInt();
        d locald30 = null;
        if (i26 != 0) {
          locald30 = d.CREATOR.a(paramParcel1);
        }
        b(locald30);
        paramParcel2.writeNoException();
        return true;
      case 5003: 
        paramParcel1.enforceInterface("com.google.android.gms.games.internal.IGamesCallbacks");
        onAchievementUpdated(paramParcel1.readInt(), paramParcel1.readString());
        paramParcel2.writeNoException();
        return true;
      case 5004: 
        paramParcel1.enforceInterface("com.google.android.gms.games.internal.IGamesCallbacks");
        int i25 = paramParcel1.readInt();
        d locald29 = null;
        if (i25 != 0) {
          locald29 = d.CREATOR.a(paramParcel1);
        }
        c(locald29);
        paramParcel2.writeNoException();
        return true;
      case 5005: 
        paramParcel1.enforceInterface("com.google.android.gms.games.internal.IGamesCallbacks");
        if (paramParcel1.readInt() != 0) {}
        for (d locald27 = d.CREATOR.a(paramParcel1);; locald27 = null)
        {
          int i24 = paramParcel1.readInt();
          d locald28 = null;
          if (i24 != 0) {
            locald28 = d.CREATOR.a(paramParcel1);
          }
          a(locald27, locald28);
          paramParcel2.writeNoException();
          return true;
        }
      case 5006: 
        paramParcel1.enforceInterface("com.google.android.gms.games.internal.IGamesCallbacks");
        int i23 = paramParcel1.readInt();
        d locald26 = null;
        if (i23 != 0) {
          locald26 = d.CREATOR.a(paramParcel1);
        }
        d(locald26);
        paramParcel2.writeNoException();
        return true;
      case 5007: 
        paramParcel1.enforceInterface("com.google.android.gms.games.internal.IGamesCallbacks");
        int i22 = paramParcel1.readInt();
        d locald25 = null;
        if (i22 != 0) {
          locald25 = d.CREATOR.a(paramParcel1);
        }
        e(locald25);
        paramParcel2.writeNoException();
        return true;
      case 5008: 
        paramParcel1.enforceInterface("com.google.android.gms.games.internal.IGamesCallbacks");
        int i21 = paramParcel1.readInt();
        d locald24 = null;
        if (i21 != 0) {
          locald24 = d.CREATOR.a(paramParcel1);
        }
        f(locald24);
        paramParcel2.writeNoException();
        return true;
      case 5009: 
        paramParcel1.enforceInterface("com.google.android.gms.games.internal.IGamesCallbacks");
        int i20 = paramParcel1.readInt();
        d locald23 = null;
        if (i20 != 0) {
          locald23 = d.CREATOR.a(paramParcel1);
        }
        g(locald23);
        paramParcel2.writeNoException();
        return true;
      case 5010: 
        paramParcel1.enforceInterface("com.google.android.gms.games.internal.IGamesCallbacks");
        int i19 = paramParcel1.readInt();
        d locald22 = null;
        if (i19 != 0) {
          locald22 = d.CREATOR.a(paramParcel1);
        }
        h(locald22);
        paramParcel2.writeNoException();
        return true;
      case 5011: 
        paramParcel1.enforceInterface("com.google.android.gms.games.internal.IGamesCallbacks");
        int i18 = paramParcel1.readInt();
        d locald21 = null;
        if (i18 != 0) {
          locald21 = d.CREATOR.a(paramParcel1);
        }
        i(locald21);
        paramParcel2.writeNoException();
        return true;
      case 5012: 
        paramParcel1.enforceInterface("com.google.android.gms.games.internal.IGamesCallbacks");
        int i17 = paramParcel1.readInt();
        d locald20 = null;
        if (i17 != 0) {
          locald20 = d.CREATOR.a(paramParcel1);
        }
        l(locald20);
        paramParcel2.writeNoException();
        return true;
      case 5013: 
        paramParcel1.enforceInterface("com.google.android.gms.games.internal.IGamesCallbacks");
        B(paramParcel1.readInt());
        paramParcel2.writeNoException();
        return true;
      case 5014: 
        paramParcel1.enforceInterface("com.google.android.gms.games.internal.IGamesCallbacks");
        int i16 = paramParcel1.readInt();
        d locald19 = null;
        if (i16 != 0) {
          locald19 = d.CREATOR.a(paramParcel1);
        }
        m(locald19);
        paramParcel2.writeNoException();
        return true;
      case 5015: 
        paramParcel1.enforceInterface("com.google.android.gms.games.internal.IGamesCallbacks");
        C(paramParcel1.readInt());
        paramParcel2.writeNoException();
        return true;
      case 5016: 
        paramParcel1.enforceInterface("com.google.android.gms.games.internal.IGamesCallbacks");
        onSignOutComplete();
        paramParcel2.writeNoException();
        return true;
      case 5017: 
        paramParcel1.enforceInterface("com.google.android.gms.games.internal.IGamesCallbacks");
        int i15 = paramParcel1.readInt();
        d locald18 = null;
        if (i15 != 0) {
          locald18 = d.CREATOR.a(paramParcel1);
        }
        j(locald18);
        paramParcel2.writeNoException();
        return true;
      case 5037: 
        paramParcel1.enforceInterface("com.google.android.gms.games.internal.IGamesCallbacks");
        int i14 = paramParcel1.readInt();
        d locald17 = null;
        if (i14 != 0) {
          locald17 = d.CREATOR.a(paramParcel1);
        }
        k(locald17);
        paramParcel2.writeNoException();
        return true;
      case 5018: 
        paramParcel1.enforceInterface("com.google.android.gms.games.internal.IGamesCallbacks");
        int i13 = paramParcel1.readInt();
        d locald16 = null;
        if (i13 != 0) {
          locald16 = d.CREATOR.a(paramParcel1);
        }
        n(locald16);
        paramParcel2.writeNoException();
        return true;
      case 5019: 
        paramParcel1.enforceInterface("com.google.android.gms.games.internal.IGamesCallbacks");
        int i12 = paramParcel1.readInt();
        d locald15 = null;
        if (i12 != 0) {
          locald15 = d.CREATOR.a(paramParcel1);
        }
        o(locald15);
        paramParcel2.writeNoException();
        return true;
      case 5020: 
        paramParcel1.enforceInterface("com.google.android.gms.games.internal.IGamesCallbacks");
        onLeftRoom(paramParcel1.readInt(), paramParcel1.readString());
        paramParcel2.writeNoException();
        return true;
      case 5021: 
        paramParcel1.enforceInterface("com.google.android.gms.games.internal.IGamesCallbacks");
        int i11 = paramParcel1.readInt();
        d locald14 = null;
        if (i11 != 0) {
          locald14 = d.CREATOR.a(paramParcel1);
        }
        p(locald14);
        paramParcel2.writeNoException();
        return true;
      case 5022: 
        paramParcel1.enforceInterface("com.google.android.gms.games.internal.IGamesCallbacks");
        int i10 = paramParcel1.readInt();
        d locald13 = null;
        if (i10 != 0) {
          locald13 = d.CREATOR.a(paramParcel1);
        }
        q(locald13);
        paramParcel2.writeNoException();
        return true;
      case 5023: 
        paramParcel1.enforceInterface("com.google.android.gms.games.internal.IGamesCallbacks");
        int i9 = paramParcel1.readInt();
        d locald12 = null;
        if (i9 != 0) {
          locald12 = d.CREATOR.a(paramParcel1);
        }
        r(locald12);
        paramParcel2.writeNoException();
        return true;
      case 5024: 
        paramParcel1.enforceInterface("com.google.android.gms.games.internal.IGamesCallbacks");
        int i8 = paramParcel1.readInt();
        d locald11 = null;
        if (i8 != 0) {
          locald11 = d.CREATOR.a(paramParcel1);
        }
        s(locald11);
        paramParcel2.writeNoException();
        return true;
      case 5025: 
        paramParcel1.enforceInterface("com.google.android.gms.games.internal.IGamesCallbacks");
        int i7 = paramParcel1.readInt();
        d locald10 = null;
        if (i7 != 0) {
          locald10 = d.CREATOR.a(paramParcel1);
        }
        t(locald10);
        paramParcel2.writeNoException();
        return true;
      case 5026: 
        paramParcel1.enforceInterface("com.google.android.gms.games.internal.IGamesCallbacks");
        int i6 = paramParcel1.readInt();
        d locald9 = null;
        if (i6 != 0) {
          locald9 = d.CREATOR.a(paramParcel1);
        }
        a(locald9, paramParcel1.createStringArray());
        paramParcel2.writeNoException();
        return true;
      case 5027: 
        paramParcel1.enforceInterface("com.google.android.gms.games.internal.IGamesCallbacks");
        int i5 = paramParcel1.readInt();
        d locald8 = null;
        if (i5 != 0) {
          locald8 = d.CREATOR.a(paramParcel1);
        }
        b(locald8, paramParcel1.createStringArray());
        paramParcel2.writeNoException();
        return true;
      case 5028: 
        paramParcel1.enforceInterface("com.google.android.gms.games.internal.IGamesCallbacks");
        int i4 = paramParcel1.readInt();
        d locald7 = null;
        if (i4 != 0) {
          locald7 = d.CREATOR.a(paramParcel1);
        }
        c(locald7, paramParcel1.createStringArray());
        paramParcel2.writeNoException();
        return true;
      case 5029: 
        paramParcel1.enforceInterface("com.google.android.gms.games.internal.IGamesCallbacks");
        int i3 = paramParcel1.readInt();
        d locald6 = null;
        if (i3 != 0) {
          locald6 = d.CREATOR.a(paramParcel1);
        }
        d(locald6, paramParcel1.createStringArray());
        paramParcel2.writeNoException();
        return true;
      case 5030: 
        paramParcel1.enforceInterface("com.google.android.gms.games.internal.IGamesCallbacks");
        int i2 = paramParcel1.readInt();
        d locald5 = null;
        if (i2 != 0) {
          locald5 = d.CREATOR.a(paramParcel1);
        }
        e(locald5, paramParcel1.createStringArray());
        paramParcel2.writeNoException();
        return true;
      case 5031: 
        paramParcel1.enforceInterface("com.google.android.gms.games.internal.IGamesCallbacks");
        int i1 = paramParcel1.readInt();
        d locald4 = null;
        if (i1 != 0) {
          locald4 = d.CREATOR.a(paramParcel1);
        }
        f(locald4, paramParcel1.createStringArray());
        paramParcel2.writeNoException();
        return true;
      case 5032: 
        paramParcel1.enforceInterface("com.google.android.gms.games.internal.IGamesCallbacks");
        int n = paramParcel1.readInt();
        RealTimeMessage localRealTimeMessage = null;
        if (n != 0) {
          localRealTimeMessage = (RealTimeMessage)RealTimeMessage.CREATOR.createFromParcel(paramParcel1);
        }
        onRealTimeMessageReceived(localRealTimeMessage);
        paramParcel2.writeNoException();
        return true;
      case 5033: 
        paramParcel1.enforceInterface("com.google.android.gms.games.internal.IGamesCallbacks");
        a(paramParcel1.readInt(), paramParcel1.readInt(), paramParcel1.readString());
        paramParcel2.writeNoException();
        return true;
      case 5034: 
        paramParcel1.enforceInterface("com.google.android.gms.games.internal.IGamesCallbacks");
        int m = paramParcel1.readInt();
        String str = paramParcel1.readString();
        if (paramParcel1.readInt() != 0) {}
        for (boolean bool = true;; bool = false)
        {
          a(m, str, bool);
          paramParcel2.writeNoException();
          return true;
        }
      case 5038: 
        paramParcel1.enforceInterface("com.google.android.gms.games.internal.IGamesCallbacks");
        int k = paramParcel1.readInt();
        d locald3 = null;
        if (k != 0) {
          locald3 = d.CREATOR.a(paramParcel1);
        }
        u(locald3);
        paramParcel2.writeNoException();
        return true;
      case 5035: 
        paramParcel1.enforceInterface("com.google.android.gms.games.internal.IGamesCallbacks");
        int j = paramParcel1.readInt();
        d locald2 = null;
        if (j != 0) {
          locald2 = d.CREATOR.a(paramParcel1);
        }
        v(locald2);
        paramParcel2.writeNoException();
        return true;
      case 5036: 
        paramParcel1.enforceInterface("com.google.android.gms.games.internal.IGamesCallbacks");
        D(paramParcel1.readInt());
        paramParcel2.writeNoException();
        return true;
      case 5039: 
        paramParcel1.enforceInterface("com.google.android.gms.games.internal.IGamesCallbacks");
        int i = paramParcel1.readInt();
        d locald1 = null;
        if (i != 0) {
          locald1 = d.CREATOR.a(paramParcel1);
        }
        w(locald1);
        paramParcel2.writeNoException();
        return true;
      case 5040: 
        paramParcel1.enforceInterface("com.google.android.gms.games.internal.IGamesCallbacks");
        E(paramParcel1.readInt());
        paramParcel2.writeNoException();
        return true;
      case 6001: 
        paramParcel1.enforceInterface("com.google.android.gms.games.internal.IGamesCallbacks");
        onP2PConnected(paramParcel1.readString());
        paramParcel2.writeNoException();
        return true;
      }
      paramParcel1.enforceInterface("com.google.android.gms.games.internal.IGamesCallbacks");
      onP2PDisconnected(paramParcel1.readString());
      paramParcel2.writeNoException();
      return true;
    }
    
    private static class a
      implements ay
    {
      private IBinder a;
      
      a(IBinder paramIBinder)
      {
        this.a = paramIBinder;
      }
      
      public void B(int paramInt)
        throws RemoteException
      {
        Parcel localParcel1 = Parcel.obtain();
        Parcel localParcel2 = Parcel.obtain();
        try
        {
          localParcel1.writeInterfaceToken("com.google.android.gms.games.internal.IGamesCallbacks");
          localParcel1.writeInt(paramInt);
          this.a.transact(5013, localParcel1, localParcel2, 0);
          localParcel2.readException();
          return;
        }
        finally
        {
          localParcel2.recycle();
          localParcel1.recycle();
        }
      }
      
      public void C(int paramInt)
        throws RemoteException
      {
        Parcel localParcel1 = Parcel.obtain();
        Parcel localParcel2 = Parcel.obtain();
        try
        {
          localParcel1.writeInterfaceToken("com.google.android.gms.games.internal.IGamesCallbacks");
          localParcel1.writeInt(paramInt);
          this.a.transact(5015, localParcel1, localParcel2, 0);
          localParcel2.readException();
          return;
        }
        finally
        {
          localParcel2.recycle();
          localParcel1.recycle();
        }
      }
      
      public void D(int paramInt)
        throws RemoteException
      {
        Parcel localParcel1 = Parcel.obtain();
        Parcel localParcel2 = Parcel.obtain();
        try
        {
          localParcel1.writeInterfaceToken("com.google.android.gms.games.internal.IGamesCallbacks");
          localParcel1.writeInt(paramInt);
          this.a.transact(5036, localParcel1, localParcel2, 0);
          localParcel2.readException();
          return;
        }
        finally
        {
          localParcel2.recycle();
          localParcel1.recycle();
        }
      }
      
      public void E(int paramInt)
        throws RemoteException
      {
        Parcel localParcel1 = Parcel.obtain();
        Parcel localParcel2 = Parcel.obtain();
        try
        {
          localParcel1.writeInterfaceToken("com.google.android.gms.games.internal.IGamesCallbacks");
          localParcel1.writeInt(paramInt);
          this.a.transact(5040, localParcel1, localParcel2, 0);
          localParcel2.readException();
          return;
        }
        finally
        {
          localParcel2.recycle();
          localParcel1.recycle();
        }
      }
      
      public void a(int paramInt1, int paramInt2, String paramString)
        throws RemoteException
      {
        Parcel localParcel1 = Parcel.obtain();
        Parcel localParcel2 = Parcel.obtain();
        try
        {
          localParcel1.writeInterfaceToken("com.google.android.gms.games.internal.IGamesCallbacks");
          localParcel1.writeInt(paramInt1);
          localParcel1.writeInt(paramInt2);
          localParcel1.writeString(paramString);
          this.a.transact(5033, localParcel1, localParcel2, 0);
          localParcel2.readException();
          return;
        }
        finally
        {
          localParcel2.recycle();
          localParcel1.recycle();
        }
      }
      
      public void a(int paramInt, String paramString)
        throws RemoteException
      {
        Parcel localParcel1 = Parcel.obtain();
        Parcel localParcel2 = Parcel.obtain();
        try
        {
          localParcel1.writeInterfaceToken("com.google.android.gms.games.internal.IGamesCallbacks");
          localParcel1.writeInt(paramInt);
          localParcel1.writeString(paramString);
          this.a.transact(5001, localParcel1, localParcel2, 0);
          localParcel2.readException();
          return;
        }
        finally
        {
          localParcel2.recycle();
          localParcel1.recycle();
        }
      }
      
      public void a(int paramInt, String paramString, boolean paramBoolean)
        throws RemoteException
      {
        Parcel localParcel1 = Parcel.obtain();
        Parcel localParcel2 = Parcel.obtain();
        try
        {
          localParcel1.writeInterfaceToken("com.google.android.gms.games.internal.IGamesCallbacks");
          localParcel1.writeInt(paramInt);
          localParcel1.writeString(paramString);
          int i = 0;
          if (paramBoolean) {
            i = 1;
          }
          localParcel1.writeInt(i);
          this.a.transact(5034, localParcel1, localParcel2, 0);
          localParcel2.readException();
          return;
        }
        finally
        {
          localParcel2.recycle();
          localParcel1.recycle();
        }
      }
      
      public void a(d paramd1, d paramd2)
        throws RemoteException
      {
        Parcel localParcel1 = Parcel.obtain();
        Parcel localParcel2 = Parcel.obtain();
        for (;;)
        {
          try
          {
            localParcel1.writeInterfaceToken("com.google.android.gms.games.internal.IGamesCallbacks");
            if (paramd1 != null)
            {
              localParcel1.writeInt(1);
              paramd1.writeToParcel(localParcel1, 0);
              if (paramd2 != null)
              {
                localParcel1.writeInt(1);
                paramd2.writeToParcel(localParcel1, 0);
                this.a.transact(5005, localParcel1, localParcel2, 0);
                localParcel2.readException();
              }
            }
            else
            {
              localParcel1.writeInt(0);
              continue;
            }
            localParcel1.writeInt(0);
          }
          finally
          {
            localParcel2.recycle();
            localParcel1.recycle();
          }
        }
      }
      
      /* Error */
      public void a(d paramd, String[] paramArrayOfString)
        throws RemoteException
      {
        // Byte code:
        //   0: invokestatic 25	android/os/Parcel:obtain	()Landroid/os/Parcel;
        //   3: astore_3
        //   4: invokestatic 25	android/os/Parcel:obtain	()Landroid/os/Parcel;
        //   7: astore 4
        //   9: aload_3
        //   10: ldc 27
        //   12: invokevirtual 31	android/os/Parcel:writeInterfaceToken	(Ljava/lang/String;)V
        //   15: aload_1
        //   16: ifnull +51 -> 67
        //   19: aload_3
        //   20: iconst_1
        //   21: invokevirtual 34	android/os/Parcel:writeInt	(I)V
        //   24: aload_1
        //   25: aload_3
        //   26: iconst_0
        //   27: invokevirtual 62	com/google/android/gms/common/data/d:writeToParcel	(Landroid/os/Parcel;I)V
        //   30: aload_3
        //   31: aload_2
        //   32: invokevirtual 67	android/os/Parcel:writeStringArray	([Ljava/lang/String;)V
        //   35: aload_0
        //   36: getfield 15	com/google/android/gms/internal/ay$a$a:a	Landroid/os/IBinder;
        //   39: sipush 5026
        //   42: aload_3
        //   43: aload 4
        //   45: iconst_0
        //   46: invokeinterface 40 5 0
        //   51: pop
        //   52: aload 4
        //   54: invokevirtual 43	android/os/Parcel:readException	()V
        //   57: aload 4
        //   59: invokevirtual 46	android/os/Parcel:recycle	()V
        //   62: aload_3
        //   63: invokevirtual 46	android/os/Parcel:recycle	()V
        //   66: return
        //   67: aload_3
        //   68: iconst_0
        //   69: invokevirtual 34	android/os/Parcel:writeInt	(I)V
        //   72: goto -42 -> 30
        //   75: astore 5
        //   77: aload 4
        //   79: invokevirtual 46	android/os/Parcel:recycle	()V
        //   82: aload_3
        //   83: invokevirtual 46	android/os/Parcel:recycle	()V
        //   86: aload 5
        //   88: athrow
        // Local variable table:
        //   start	length	slot	name	signature
        //   0	89	0	this	a
        //   0	89	1	paramd	d
        //   0	89	2	paramArrayOfString	String[]
        //   3	80	3	localParcel1	Parcel
        //   7	71	4	localParcel2	Parcel
        //   75	12	5	localObject	Object
        // Exception table:
        //   from	to	target	type
        //   9	15	75	finally
        //   19	30	75	finally
        //   30	57	75	finally
        //   67	72	75	finally
      }
      
      public IBinder asBinder()
      {
        return this.a;
      }
      
      /* Error */
      public void b(d paramd)
        throws RemoteException
      {
        // Byte code:
        //   0: invokestatic 25	android/os/Parcel:obtain	()Landroid/os/Parcel;
        //   3: astore_2
        //   4: invokestatic 25	android/os/Parcel:obtain	()Landroid/os/Parcel;
        //   7: astore_3
        //   8: aload_2
        //   9: ldc 27
        //   11: invokevirtual 31	android/os/Parcel:writeInterfaceToken	(Ljava/lang/String;)V
        //   14: aload_1
        //   15: ifnull +43 -> 58
        //   18: aload_2
        //   19: iconst_1
        //   20: invokevirtual 34	android/os/Parcel:writeInt	(I)V
        //   23: aload_1
        //   24: aload_2
        //   25: iconst_0
        //   26: invokevirtual 62	com/google/android/gms/common/data/d:writeToParcel	(Landroid/os/Parcel;I)V
        //   29: aload_0
        //   30: getfield 15	com/google/android/gms/internal/ay$a$a:a	Landroid/os/IBinder;
        //   33: sipush 5002
        //   36: aload_2
        //   37: aload_3
        //   38: iconst_0
        //   39: invokeinterface 40 5 0
        //   44: pop
        //   45: aload_3
        //   46: invokevirtual 43	android/os/Parcel:readException	()V
        //   49: aload_3
        //   50: invokevirtual 46	android/os/Parcel:recycle	()V
        //   53: aload_2
        //   54: invokevirtual 46	android/os/Parcel:recycle	()V
        //   57: return
        //   58: aload_2
        //   59: iconst_0
        //   60: invokevirtual 34	android/os/Parcel:writeInt	(I)V
        //   63: goto -34 -> 29
        //   66: astore 4
        //   68: aload_3
        //   69: invokevirtual 46	android/os/Parcel:recycle	()V
        //   72: aload_2
        //   73: invokevirtual 46	android/os/Parcel:recycle	()V
        //   76: aload 4
        //   78: athrow
        // Local variable table:
        //   start	length	slot	name	signature
        //   0	79	0	this	a
        //   0	79	1	paramd	d
        //   3	70	2	localParcel1	Parcel
        //   7	62	3	localParcel2	Parcel
        //   66	11	4	localObject	Object
        // Exception table:
        //   from	to	target	type
        //   8	14	66	finally
        //   18	29	66	finally
        //   29	49	66	finally
        //   58	63	66	finally
      }
      
      /* Error */
      public void b(d paramd, String[] paramArrayOfString)
        throws RemoteException
      {
        // Byte code:
        //   0: invokestatic 25	android/os/Parcel:obtain	()Landroid/os/Parcel;
        //   3: astore_3
        //   4: invokestatic 25	android/os/Parcel:obtain	()Landroid/os/Parcel;
        //   7: astore 4
        //   9: aload_3
        //   10: ldc 27
        //   12: invokevirtual 31	android/os/Parcel:writeInterfaceToken	(Ljava/lang/String;)V
        //   15: aload_1
        //   16: ifnull +51 -> 67
        //   19: aload_3
        //   20: iconst_1
        //   21: invokevirtual 34	android/os/Parcel:writeInt	(I)V
        //   24: aload_1
        //   25: aload_3
        //   26: iconst_0
        //   27: invokevirtual 62	com/google/android/gms/common/data/d:writeToParcel	(Landroid/os/Parcel;I)V
        //   30: aload_3
        //   31: aload_2
        //   32: invokevirtual 67	android/os/Parcel:writeStringArray	([Ljava/lang/String;)V
        //   35: aload_0
        //   36: getfield 15	com/google/android/gms/internal/ay$a$a:a	Landroid/os/IBinder;
        //   39: sipush 5027
        //   42: aload_3
        //   43: aload 4
        //   45: iconst_0
        //   46: invokeinterface 40 5 0
        //   51: pop
        //   52: aload 4
        //   54: invokevirtual 43	android/os/Parcel:readException	()V
        //   57: aload 4
        //   59: invokevirtual 46	android/os/Parcel:recycle	()V
        //   62: aload_3
        //   63: invokevirtual 46	android/os/Parcel:recycle	()V
        //   66: return
        //   67: aload_3
        //   68: iconst_0
        //   69: invokevirtual 34	android/os/Parcel:writeInt	(I)V
        //   72: goto -42 -> 30
        //   75: astore 5
        //   77: aload 4
        //   79: invokevirtual 46	android/os/Parcel:recycle	()V
        //   82: aload_3
        //   83: invokevirtual 46	android/os/Parcel:recycle	()V
        //   86: aload 5
        //   88: athrow
        // Local variable table:
        //   start	length	slot	name	signature
        //   0	89	0	this	a
        //   0	89	1	paramd	d
        //   0	89	2	paramArrayOfString	String[]
        //   3	80	3	localParcel1	Parcel
        //   7	71	4	localParcel2	Parcel
        //   75	12	5	localObject	Object
        // Exception table:
        //   from	to	target	type
        //   9	15	75	finally
        //   19	30	75	finally
        //   30	57	75	finally
        //   67	72	75	finally
      }
      
      /* Error */
      public void c(d paramd)
        throws RemoteException
      {
        // Byte code:
        //   0: invokestatic 25	android/os/Parcel:obtain	()Landroid/os/Parcel;
        //   3: astore_2
        //   4: invokestatic 25	android/os/Parcel:obtain	()Landroid/os/Parcel;
        //   7: astore_3
        //   8: aload_2
        //   9: ldc 27
        //   11: invokevirtual 31	android/os/Parcel:writeInterfaceToken	(Ljava/lang/String;)V
        //   14: aload_1
        //   15: ifnull +43 -> 58
        //   18: aload_2
        //   19: iconst_1
        //   20: invokevirtual 34	android/os/Parcel:writeInt	(I)V
        //   23: aload_1
        //   24: aload_2
        //   25: iconst_0
        //   26: invokevirtual 62	com/google/android/gms/common/data/d:writeToParcel	(Landroid/os/Parcel;I)V
        //   29: aload_0
        //   30: getfield 15	com/google/android/gms/internal/ay$a$a:a	Landroid/os/IBinder;
        //   33: sipush 5004
        //   36: aload_2
        //   37: aload_3
        //   38: iconst_0
        //   39: invokeinterface 40 5 0
        //   44: pop
        //   45: aload_3
        //   46: invokevirtual 43	android/os/Parcel:readException	()V
        //   49: aload_3
        //   50: invokevirtual 46	android/os/Parcel:recycle	()V
        //   53: aload_2
        //   54: invokevirtual 46	android/os/Parcel:recycle	()V
        //   57: return
        //   58: aload_2
        //   59: iconst_0
        //   60: invokevirtual 34	android/os/Parcel:writeInt	(I)V
        //   63: goto -34 -> 29
        //   66: astore 4
        //   68: aload_3
        //   69: invokevirtual 46	android/os/Parcel:recycle	()V
        //   72: aload_2
        //   73: invokevirtual 46	android/os/Parcel:recycle	()V
        //   76: aload 4
        //   78: athrow
        // Local variable table:
        //   start	length	slot	name	signature
        //   0	79	0	this	a
        //   0	79	1	paramd	d
        //   3	70	2	localParcel1	Parcel
        //   7	62	3	localParcel2	Parcel
        //   66	11	4	localObject	Object
        // Exception table:
        //   from	to	target	type
        //   8	14	66	finally
        //   18	29	66	finally
        //   29	49	66	finally
        //   58	63	66	finally
      }
      
      /* Error */
      public void c(d paramd, String[] paramArrayOfString)
        throws RemoteException
      {
        // Byte code:
        //   0: invokestatic 25	android/os/Parcel:obtain	()Landroid/os/Parcel;
        //   3: astore_3
        //   4: invokestatic 25	android/os/Parcel:obtain	()Landroid/os/Parcel;
        //   7: astore 4
        //   9: aload_3
        //   10: ldc 27
        //   12: invokevirtual 31	android/os/Parcel:writeInterfaceToken	(Ljava/lang/String;)V
        //   15: aload_1
        //   16: ifnull +51 -> 67
        //   19: aload_3
        //   20: iconst_1
        //   21: invokevirtual 34	android/os/Parcel:writeInt	(I)V
        //   24: aload_1
        //   25: aload_3
        //   26: iconst_0
        //   27: invokevirtual 62	com/google/android/gms/common/data/d:writeToParcel	(Landroid/os/Parcel;I)V
        //   30: aload_3
        //   31: aload_2
        //   32: invokevirtual 67	android/os/Parcel:writeStringArray	([Ljava/lang/String;)V
        //   35: aload_0
        //   36: getfield 15	com/google/android/gms/internal/ay$a$a:a	Landroid/os/IBinder;
        //   39: sipush 5028
        //   42: aload_3
        //   43: aload 4
        //   45: iconst_0
        //   46: invokeinterface 40 5 0
        //   51: pop
        //   52: aload 4
        //   54: invokevirtual 43	android/os/Parcel:readException	()V
        //   57: aload 4
        //   59: invokevirtual 46	android/os/Parcel:recycle	()V
        //   62: aload_3
        //   63: invokevirtual 46	android/os/Parcel:recycle	()V
        //   66: return
        //   67: aload_3
        //   68: iconst_0
        //   69: invokevirtual 34	android/os/Parcel:writeInt	(I)V
        //   72: goto -42 -> 30
        //   75: astore 5
        //   77: aload 4
        //   79: invokevirtual 46	android/os/Parcel:recycle	()V
        //   82: aload_3
        //   83: invokevirtual 46	android/os/Parcel:recycle	()V
        //   86: aload 5
        //   88: athrow
        // Local variable table:
        //   start	length	slot	name	signature
        //   0	89	0	this	a
        //   0	89	1	paramd	d
        //   0	89	2	paramArrayOfString	String[]
        //   3	80	3	localParcel1	Parcel
        //   7	71	4	localParcel2	Parcel
        //   75	12	5	localObject	Object
        // Exception table:
        //   from	to	target	type
        //   9	15	75	finally
        //   19	30	75	finally
        //   30	57	75	finally
        //   67	72	75	finally
      }
      
      /* Error */
      public void d(d paramd)
        throws RemoteException
      {
        // Byte code:
        //   0: invokestatic 25	android/os/Parcel:obtain	()Landroid/os/Parcel;
        //   3: astore_2
        //   4: invokestatic 25	android/os/Parcel:obtain	()Landroid/os/Parcel;
        //   7: astore_3
        //   8: aload_2
        //   9: ldc 27
        //   11: invokevirtual 31	android/os/Parcel:writeInterfaceToken	(Ljava/lang/String;)V
        //   14: aload_1
        //   15: ifnull +43 -> 58
        //   18: aload_2
        //   19: iconst_1
        //   20: invokevirtual 34	android/os/Parcel:writeInt	(I)V
        //   23: aload_1
        //   24: aload_2
        //   25: iconst_0
        //   26: invokevirtual 62	com/google/android/gms/common/data/d:writeToParcel	(Landroid/os/Parcel;I)V
        //   29: aload_0
        //   30: getfield 15	com/google/android/gms/internal/ay$a$a:a	Landroid/os/IBinder;
        //   33: sipush 5006
        //   36: aload_2
        //   37: aload_3
        //   38: iconst_0
        //   39: invokeinterface 40 5 0
        //   44: pop
        //   45: aload_3
        //   46: invokevirtual 43	android/os/Parcel:readException	()V
        //   49: aload_3
        //   50: invokevirtual 46	android/os/Parcel:recycle	()V
        //   53: aload_2
        //   54: invokevirtual 46	android/os/Parcel:recycle	()V
        //   57: return
        //   58: aload_2
        //   59: iconst_0
        //   60: invokevirtual 34	android/os/Parcel:writeInt	(I)V
        //   63: goto -34 -> 29
        //   66: astore 4
        //   68: aload_3
        //   69: invokevirtual 46	android/os/Parcel:recycle	()V
        //   72: aload_2
        //   73: invokevirtual 46	android/os/Parcel:recycle	()V
        //   76: aload 4
        //   78: athrow
        // Local variable table:
        //   start	length	slot	name	signature
        //   0	79	0	this	a
        //   0	79	1	paramd	d
        //   3	70	2	localParcel1	Parcel
        //   7	62	3	localParcel2	Parcel
        //   66	11	4	localObject	Object
        // Exception table:
        //   from	to	target	type
        //   8	14	66	finally
        //   18	29	66	finally
        //   29	49	66	finally
        //   58	63	66	finally
      }
      
      /* Error */
      public void d(d paramd, String[] paramArrayOfString)
        throws RemoteException
      {
        // Byte code:
        //   0: invokestatic 25	android/os/Parcel:obtain	()Landroid/os/Parcel;
        //   3: astore_3
        //   4: invokestatic 25	android/os/Parcel:obtain	()Landroid/os/Parcel;
        //   7: astore 4
        //   9: aload_3
        //   10: ldc 27
        //   12: invokevirtual 31	android/os/Parcel:writeInterfaceToken	(Ljava/lang/String;)V
        //   15: aload_1
        //   16: ifnull +51 -> 67
        //   19: aload_3
        //   20: iconst_1
        //   21: invokevirtual 34	android/os/Parcel:writeInt	(I)V
        //   24: aload_1
        //   25: aload_3
        //   26: iconst_0
        //   27: invokevirtual 62	com/google/android/gms/common/data/d:writeToParcel	(Landroid/os/Parcel;I)V
        //   30: aload_3
        //   31: aload_2
        //   32: invokevirtual 67	android/os/Parcel:writeStringArray	([Ljava/lang/String;)V
        //   35: aload_0
        //   36: getfield 15	com/google/android/gms/internal/ay$a$a:a	Landroid/os/IBinder;
        //   39: sipush 5029
        //   42: aload_3
        //   43: aload 4
        //   45: iconst_0
        //   46: invokeinterface 40 5 0
        //   51: pop
        //   52: aload 4
        //   54: invokevirtual 43	android/os/Parcel:readException	()V
        //   57: aload 4
        //   59: invokevirtual 46	android/os/Parcel:recycle	()V
        //   62: aload_3
        //   63: invokevirtual 46	android/os/Parcel:recycle	()V
        //   66: return
        //   67: aload_3
        //   68: iconst_0
        //   69: invokevirtual 34	android/os/Parcel:writeInt	(I)V
        //   72: goto -42 -> 30
        //   75: astore 5
        //   77: aload 4
        //   79: invokevirtual 46	android/os/Parcel:recycle	()V
        //   82: aload_3
        //   83: invokevirtual 46	android/os/Parcel:recycle	()V
        //   86: aload 5
        //   88: athrow
        // Local variable table:
        //   start	length	slot	name	signature
        //   0	89	0	this	a
        //   0	89	1	paramd	d
        //   0	89	2	paramArrayOfString	String[]
        //   3	80	3	localParcel1	Parcel
        //   7	71	4	localParcel2	Parcel
        //   75	12	5	localObject	Object
        // Exception table:
        //   from	to	target	type
        //   9	15	75	finally
        //   19	30	75	finally
        //   30	57	75	finally
        //   67	72	75	finally
      }
      
      /* Error */
      public void e(d paramd)
        throws RemoteException
      {
        // Byte code:
        //   0: invokestatic 25	android/os/Parcel:obtain	()Landroid/os/Parcel;
        //   3: astore_2
        //   4: invokestatic 25	android/os/Parcel:obtain	()Landroid/os/Parcel;
        //   7: astore_3
        //   8: aload_2
        //   9: ldc 27
        //   11: invokevirtual 31	android/os/Parcel:writeInterfaceToken	(Ljava/lang/String;)V
        //   14: aload_1
        //   15: ifnull +43 -> 58
        //   18: aload_2
        //   19: iconst_1
        //   20: invokevirtual 34	android/os/Parcel:writeInt	(I)V
        //   23: aload_1
        //   24: aload_2
        //   25: iconst_0
        //   26: invokevirtual 62	com/google/android/gms/common/data/d:writeToParcel	(Landroid/os/Parcel;I)V
        //   29: aload_0
        //   30: getfield 15	com/google/android/gms/internal/ay$a$a:a	Landroid/os/IBinder;
        //   33: sipush 5007
        //   36: aload_2
        //   37: aload_3
        //   38: iconst_0
        //   39: invokeinterface 40 5 0
        //   44: pop
        //   45: aload_3
        //   46: invokevirtual 43	android/os/Parcel:readException	()V
        //   49: aload_3
        //   50: invokevirtual 46	android/os/Parcel:recycle	()V
        //   53: aload_2
        //   54: invokevirtual 46	android/os/Parcel:recycle	()V
        //   57: return
        //   58: aload_2
        //   59: iconst_0
        //   60: invokevirtual 34	android/os/Parcel:writeInt	(I)V
        //   63: goto -34 -> 29
        //   66: astore 4
        //   68: aload_3
        //   69: invokevirtual 46	android/os/Parcel:recycle	()V
        //   72: aload_2
        //   73: invokevirtual 46	android/os/Parcel:recycle	()V
        //   76: aload 4
        //   78: athrow
        // Local variable table:
        //   start	length	slot	name	signature
        //   0	79	0	this	a
        //   0	79	1	paramd	d
        //   3	70	2	localParcel1	Parcel
        //   7	62	3	localParcel2	Parcel
        //   66	11	4	localObject	Object
        // Exception table:
        //   from	to	target	type
        //   8	14	66	finally
        //   18	29	66	finally
        //   29	49	66	finally
        //   58	63	66	finally
      }
      
      /* Error */
      public void e(d paramd, String[] paramArrayOfString)
        throws RemoteException
      {
        // Byte code:
        //   0: invokestatic 25	android/os/Parcel:obtain	()Landroid/os/Parcel;
        //   3: astore_3
        //   4: invokestatic 25	android/os/Parcel:obtain	()Landroid/os/Parcel;
        //   7: astore 4
        //   9: aload_3
        //   10: ldc 27
        //   12: invokevirtual 31	android/os/Parcel:writeInterfaceToken	(Ljava/lang/String;)V
        //   15: aload_1
        //   16: ifnull +51 -> 67
        //   19: aload_3
        //   20: iconst_1
        //   21: invokevirtual 34	android/os/Parcel:writeInt	(I)V
        //   24: aload_1
        //   25: aload_3
        //   26: iconst_0
        //   27: invokevirtual 62	com/google/android/gms/common/data/d:writeToParcel	(Landroid/os/Parcel;I)V
        //   30: aload_3
        //   31: aload_2
        //   32: invokevirtual 67	android/os/Parcel:writeStringArray	([Ljava/lang/String;)V
        //   35: aload_0
        //   36: getfield 15	com/google/android/gms/internal/ay$a$a:a	Landroid/os/IBinder;
        //   39: sipush 5030
        //   42: aload_3
        //   43: aload 4
        //   45: iconst_0
        //   46: invokeinterface 40 5 0
        //   51: pop
        //   52: aload 4
        //   54: invokevirtual 43	android/os/Parcel:readException	()V
        //   57: aload 4
        //   59: invokevirtual 46	android/os/Parcel:recycle	()V
        //   62: aload_3
        //   63: invokevirtual 46	android/os/Parcel:recycle	()V
        //   66: return
        //   67: aload_3
        //   68: iconst_0
        //   69: invokevirtual 34	android/os/Parcel:writeInt	(I)V
        //   72: goto -42 -> 30
        //   75: astore 5
        //   77: aload 4
        //   79: invokevirtual 46	android/os/Parcel:recycle	()V
        //   82: aload_3
        //   83: invokevirtual 46	android/os/Parcel:recycle	()V
        //   86: aload 5
        //   88: athrow
        // Local variable table:
        //   start	length	slot	name	signature
        //   0	89	0	this	a
        //   0	89	1	paramd	d
        //   0	89	2	paramArrayOfString	String[]
        //   3	80	3	localParcel1	Parcel
        //   7	71	4	localParcel2	Parcel
        //   75	12	5	localObject	Object
        // Exception table:
        //   from	to	target	type
        //   9	15	75	finally
        //   19	30	75	finally
        //   30	57	75	finally
        //   67	72	75	finally
      }
      
      /* Error */
      public void f(d paramd)
        throws RemoteException
      {
        // Byte code:
        //   0: invokestatic 25	android/os/Parcel:obtain	()Landroid/os/Parcel;
        //   3: astore_2
        //   4: invokestatic 25	android/os/Parcel:obtain	()Landroid/os/Parcel;
        //   7: astore_3
        //   8: aload_2
        //   9: ldc 27
        //   11: invokevirtual 31	android/os/Parcel:writeInterfaceToken	(Ljava/lang/String;)V
        //   14: aload_1
        //   15: ifnull +43 -> 58
        //   18: aload_2
        //   19: iconst_1
        //   20: invokevirtual 34	android/os/Parcel:writeInt	(I)V
        //   23: aload_1
        //   24: aload_2
        //   25: iconst_0
        //   26: invokevirtual 62	com/google/android/gms/common/data/d:writeToParcel	(Landroid/os/Parcel;I)V
        //   29: aload_0
        //   30: getfield 15	com/google/android/gms/internal/ay$a$a:a	Landroid/os/IBinder;
        //   33: sipush 5008
        //   36: aload_2
        //   37: aload_3
        //   38: iconst_0
        //   39: invokeinterface 40 5 0
        //   44: pop
        //   45: aload_3
        //   46: invokevirtual 43	android/os/Parcel:readException	()V
        //   49: aload_3
        //   50: invokevirtual 46	android/os/Parcel:recycle	()V
        //   53: aload_2
        //   54: invokevirtual 46	android/os/Parcel:recycle	()V
        //   57: return
        //   58: aload_2
        //   59: iconst_0
        //   60: invokevirtual 34	android/os/Parcel:writeInt	(I)V
        //   63: goto -34 -> 29
        //   66: astore 4
        //   68: aload_3
        //   69: invokevirtual 46	android/os/Parcel:recycle	()V
        //   72: aload_2
        //   73: invokevirtual 46	android/os/Parcel:recycle	()V
        //   76: aload 4
        //   78: athrow
        // Local variable table:
        //   start	length	slot	name	signature
        //   0	79	0	this	a
        //   0	79	1	paramd	d
        //   3	70	2	localParcel1	Parcel
        //   7	62	3	localParcel2	Parcel
        //   66	11	4	localObject	Object
        // Exception table:
        //   from	to	target	type
        //   8	14	66	finally
        //   18	29	66	finally
        //   29	49	66	finally
        //   58	63	66	finally
      }
      
      /* Error */
      public void f(d paramd, String[] paramArrayOfString)
        throws RemoteException
      {
        // Byte code:
        //   0: invokestatic 25	android/os/Parcel:obtain	()Landroid/os/Parcel;
        //   3: astore_3
        //   4: invokestatic 25	android/os/Parcel:obtain	()Landroid/os/Parcel;
        //   7: astore 4
        //   9: aload_3
        //   10: ldc 27
        //   12: invokevirtual 31	android/os/Parcel:writeInterfaceToken	(Ljava/lang/String;)V
        //   15: aload_1
        //   16: ifnull +51 -> 67
        //   19: aload_3
        //   20: iconst_1
        //   21: invokevirtual 34	android/os/Parcel:writeInt	(I)V
        //   24: aload_1
        //   25: aload_3
        //   26: iconst_0
        //   27: invokevirtual 62	com/google/android/gms/common/data/d:writeToParcel	(Landroid/os/Parcel;I)V
        //   30: aload_3
        //   31: aload_2
        //   32: invokevirtual 67	android/os/Parcel:writeStringArray	([Ljava/lang/String;)V
        //   35: aload_0
        //   36: getfield 15	com/google/android/gms/internal/ay$a$a:a	Landroid/os/IBinder;
        //   39: sipush 5031
        //   42: aload_3
        //   43: aload 4
        //   45: iconst_0
        //   46: invokeinterface 40 5 0
        //   51: pop
        //   52: aload 4
        //   54: invokevirtual 43	android/os/Parcel:readException	()V
        //   57: aload 4
        //   59: invokevirtual 46	android/os/Parcel:recycle	()V
        //   62: aload_3
        //   63: invokevirtual 46	android/os/Parcel:recycle	()V
        //   66: return
        //   67: aload_3
        //   68: iconst_0
        //   69: invokevirtual 34	android/os/Parcel:writeInt	(I)V
        //   72: goto -42 -> 30
        //   75: astore 5
        //   77: aload 4
        //   79: invokevirtual 46	android/os/Parcel:recycle	()V
        //   82: aload_3
        //   83: invokevirtual 46	android/os/Parcel:recycle	()V
        //   86: aload 5
        //   88: athrow
        // Local variable table:
        //   start	length	slot	name	signature
        //   0	89	0	this	a
        //   0	89	1	paramd	d
        //   0	89	2	paramArrayOfString	String[]
        //   3	80	3	localParcel1	Parcel
        //   7	71	4	localParcel2	Parcel
        //   75	12	5	localObject	Object
        // Exception table:
        //   from	to	target	type
        //   9	15	75	finally
        //   19	30	75	finally
        //   30	57	75	finally
        //   67	72	75	finally
      }
      
      /* Error */
      public void g(d paramd)
        throws RemoteException
      {
        // Byte code:
        //   0: invokestatic 25	android/os/Parcel:obtain	()Landroid/os/Parcel;
        //   3: astore_2
        //   4: invokestatic 25	android/os/Parcel:obtain	()Landroid/os/Parcel;
        //   7: astore_3
        //   8: aload_2
        //   9: ldc 27
        //   11: invokevirtual 31	android/os/Parcel:writeInterfaceToken	(Ljava/lang/String;)V
        //   14: aload_1
        //   15: ifnull +43 -> 58
        //   18: aload_2
        //   19: iconst_1
        //   20: invokevirtual 34	android/os/Parcel:writeInt	(I)V
        //   23: aload_1
        //   24: aload_2
        //   25: iconst_0
        //   26: invokevirtual 62	com/google/android/gms/common/data/d:writeToParcel	(Landroid/os/Parcel;I)V
        //   29: aload_0
        //   30: getfield 15	com/google/android/gms/internal/ay$a$a:a	Landroid/os/IBinder;
        //   33: sipush 5009
        //   36: aload_2
        //   37: aload_3
        //   38: iconst_0
        //   39: invokeinterface 40 5 0
        //   44: pop
        //   45: aload_3
        //   46: invokevirtual 43	android/os/Parcel:readException	()V
        //   49: aload_3
        //   50: invokevirtual 46	android/os/Parcel:recycle	()V
        //   53: aload_2
        //   54: invokevirtual 46	android/os/Parcel:recycle	()V
        //   57: return
        //   58: aload_2
        //   59: iconst_0
        //   60: invokevirtual 34	android/os/Parcel:writeInt	(I)V
        //   63: goto -34 -> 29
        //   66: astore 4
        //   68: aload_3
        //   69: invokevirtual 46	android/os/Parcel:recycle	()V
        //   72: aload_2
        //   73: invokevirtual 46	android/os/Parcel:recycle	()V
        //   76: aload 4
        //   78: athrow
        // Local variable table:
        //   start	length	slot	name	signature
        //   0	79	0	this	a
        //   0	79	1	paramd	d
        //   3	70	2	localParcel1	Parcel
        //   7	62	3	localParcel2	Parcel
        //   66	11	4	localObject	Object
        // Exception table:
        //   from	to	target	type
        //   8	14	66	finally
        //   18	29	66	finally
        //   29	49	66	finally
        //   58	63	66	finally
      }
      
      /* Error */
      public void h(d paramd)
        throws RemoteException
      {
        // Byte code:
        //   0: invokestatic 25	android/os/Parcel:obtain	()Landroid/os/Parcel;
        //   3: astore_2
        //   4: invokestatic 25	android/os/Parcel:obtain	()Landroid/os/Parcel;
        //   7: astore_3
        //   8: aload_2
        //   9: ldc 27
        //   11: invokevirtual 31	android/os/Parcel:writeInterfaceToken	(Ljava/lang/String;)V
        //   14: aload_1
        //   15: ifnull +43 -> 58
        //   18: aload_2
        //   19: iconst_1
        //   20: invokevirtual 34	android/os/Parcel:writeInt	(I)V
        //   23: aload_1
        //   24: aload_2
        //   25: iconst_0
        //   26: invokevirtual 62	com/google/android/gms/common/data/d:writeToParcel	(Landroid/os/Parcel;I)V
        //   29: aload_0
        //   30: getfield 15	com/google/android/gms/internal/ay$a$a:a	Landroid/os/IBinder;
        //   33: sipush 5010
        //   36: aload_2
        //   37: aload_3
        //   38: iconst_0
        //   39: invokeinterface 40 5 0
        //   44: pop
        //   45: aload_3
        //   46: invokevirtual 43	android/os/Parcel:readException	()V
        //   49: aload_3
        //   50: invokevirtual 46	android/os/Parcel:recycle	()V
        //   53: aload_2
        //   54: invokevirtual 46	android/os/Parcel:recycle	()V
        //   57: return
        //   58: aload_2
        //   59: iconst_0
        //   60: invokevirtual 34	android/os/Parcel:writeInt	(I)V
        //   63: goto -34 -> 29
        //   66: astore 4
        //   68: aload_3
        //   69: invokevirtual 46	android/os/Parcel:recycle	()V
        //   72: aload_2
        //   73: invokevirtual 46	android/os/Parcel:recycle	()V
        //   76: aload 4
        //   78: athrow
        // Local variable table:
        //   start	length	slot	name	signature
        //   0	79	0	this	a
        //   0	79	1	paramd	d
        //   3	70	2	localParcel1	Parcel
        //   7	62	3	localParcel2	Parcel
        //   66	11	4	localObject	Object
        // Exception table:
        //   from	to	target	type
        //   8	14	66	finally
        //   18	29	66	finally
        //   29	49	66	finally
        //   58	63	66	finally
      }
      
      /* Error */
      public void i(d paramd)
        throws RemoteException
      {
        // Byte code:
        //   0: invokestatic 25	android/os/Parcel:obtain	()Landroid/os/Parcel;
        //   3: astore_2
        //   4: invokestatic 25	android/os/Parcel:obtain	()Landroid/os/Parcel;
        //   7: astore_3
        //   8: aload_2
        //   9: ldc 27
        //   11: invokevirtual 31	android/os/Parcel:writeInterfaceToken	(Ljava/lang/String;)V
        //   14: aload_1
        //   15: ifnull +43 -> 58
        //   18: aload_2
        //   19: iconst_1
        //   20: invokevirtual 34	android/os/Parcel:writeInt	(I)V
        //   23: aload_1
        //   24: aload_2
        //   25: iconst_0
        //   26: invokevirtual 62	com/google/android/gms/common/data/d:writeToParcel	(Landroid/os/Parcel;I)V
        //   29: aload_0
        //   30: getfield 15	com/google/android/gms/internal/ay$a$a:a	Landroid/os/IBinder;
        //   33: sipush 5011
        //   36: aload_2
        //   37: aload_3
        //   38: iconst_0
        //   39: invokeinterface 40 5 0
        //   44: pop
        //   45: aload_3
        //   46: invokevirtual 43	android/os/Parcel:readException	()V
        //   49: aload_3
        //   50: invokevirtual 46	android/os/Parcel:recycle	()V
        //   53: aload_2
        //   54: invokevirtual 46	android/os/Parcel:recycle	()V
        //   57: return
        //   58: aload_2
        //   59: iconst_0
        //   60: invokevirtual 34	android/os/Parcel:writeInt	(I)V
        //   63: goto -34 -> 29
        //   66: astore 4
        //   68: aload_3
        //   69: invokevirtual 46	android/os/Parcel:recycle	()V
        //   72: aload_2
        //   73: invokevirtual 46	android/os/Parcel:recycle	()V
        //   76: aload 4
        //   78: athrow
        // Local variable table:
        //   start	length	slot	name	signature
        //   0	79	0	this	a
        //   0	79	1	paramd	d
        //   3	70	2	localParcel1	Parcel
        //   7	62	3	localParcel2	Parcel
        //   66	11	4	localObject	Object
        // Exception table:
        //   from	to	target	type
        //   8	14	66	finally
        //   18	29	66	finally
        //   29	49	66	finally
        //   58	63	66	finally
      }
      
      /* Error */
      public void j(d paramd)
        throws RemoteException
      {
        // Byte code:
        //   0: invokestatic 25	android/os/Parcel:obtain	()Landroid/os/Parcel;
        //   3: astore_2
        //   4: invokestatic 25	android/os/Parcel:obtain	()Landroid/os/Parcel;
        //   7: astore_3
        //   8: aload_2
        //   9: ldc 27
        //   11: invokevirtual 31	android/os/Parcel:writeInterfaceToken	(Ljava/lang/String;)V
        //   14: aload_1
        //   15: ifnull +43 -> 58
        //   18: aload_2
        //   19: iconst_1
        //   20: invokevirtual 34	android/os/Parcel:writeInt	(I)V
        //   23: aload_1
        //   24: aload_2
        //   25: iconst_0
        //   26: invokevirtual 62	com/google/android/gms/common/data/d:writeToParcel	(Landroid/os/Parcel;I)V
        //   29: aload_0
        //   30: getfield 15	com/google/android/gms/internal/ay$a$a:a	Landroid/os/IBinder;
        //   33: sipush 5017
        //   36: aload_2
        //   37: aload_3
        //   38: iconst_0
        //   39: invokeinterface 40 5 0
        //   44: pop
        //   45: aload_3
        //   46: invokevirtual 43	android/os/Parcel:readException	()V
        //   49: aload_3
        //   50: invokevirtual 46	android/os/Parcel:recycle	()V
        //   53: aload_2
        //   54: invokevirtual 46	android/os/Parcel:recycle	()V
        //   57: return
        //   58: aload_2
        //   59: iconst_0
        //   60: invokevirtual 34	android/os/Parcel:writeInt	(I)V
        //   63: goto -34 -> 29
        //   66: astore 4
        //   68: aload_3
        //   69: invokevirtual 46	android/os/Parcel:recycle	()V
        //   72: aload_2
        //   73: invokevirtual 46	android/os/Parcel:recycle	()V
        //   76: aload 4
        //   78: athrow
        // Local variable table:
        //   start	length	slot	name	signature
        //   0	79	0	this	a
        //   0	79	1	paramd	d
        //   3	70	2	localParcel1	Parcel
        //   7	62	3	localParcel2	Parcel
        //   66	11	4	localObject	Object
        // Exception table:
        //   from	to	target	type
        //   8	14	66	finally
        //   18	29	66	finally
        //   29	49	66	finally
        //   58	63	66	finally
      }
      
      /* Error */
      public void k(d paramd)
        throws RemoteException
      {
        // Byte code:
        //   0: invokestatic 25	android/os/Parcel:obtain	()Landroid/os/Parcel;
        //   3: astore_2
        //   4: invokestatic 25	android/os/Parcel:obtain	()Landroid/os/Parcel;
        //   7: astore_3
        //   8: aload_2
        //   9: ldc 27
        //   11: invokevirtual 31	android/os/Parcel:writeInterfaceToken	(Ljava/lang/String;)V
        //   14: aload_1
        //   15: ifnull +43 -> 58
        //   18: aload_2
        //   19: iconst_1
        //   20: invokevirtual 34	android/os/Parcel:writeInt	(I)V
        //   23: aload_1
        //   24: aload_2
        //   25: iconst_0
        //   26: invokevirtual 62	com/google/android/gms/common/data/d:writeToParcel	(Landroid/os/Parcel;I)V
        //   29: aload_0
        //   30: getfield 15	com/google/android/gms/internal/ay$a$a:a	Landroid/os/IBinder;
        //   33: sipush 5037
        //   36: aload_2
        //   37: aload_3
        //   38: iconst_0
        //   39: invokeinterface 40 5 0
        //   44: pop
        //   45: aload_3
        //   46: invokevirtual 43	android/os/Parcel:readException	()V
        //   49: aload_3
        //   50: invokevirtual 46	android/os/Parcel:recycle	()V
        //   53: aload_2
        //   54: invokevirtual 46	android/os/Parcel:recycle	()V
        //   57: return
        //   58: aload_2
        //   59: iconst_0
        //   60: invokevirtual 34	android/os/Parcel:writeInt	(I)V
        //   63: goto -34 -> 29
        //   66: astore 4
        //   68: aload_3
        //   69: invokevirtual 46	android/os/Parcel:recycle	()V
        //   72: aload_2
        //   73: invokevirtual 46	android/os/Parcel:recycle	()V
        //   76: aload 4
        //   78: athrow
        // Local variable table:
        //   start	length	slot	name	signature
        //   0	79	0	this	a
        //   0	79	1	paramd	d
        //   3	70	2	localParcel1	Parcel
        //   7	62	3	localParcel2	Parcel
        //   66	11	4	localObject	Object
        // Exception table:
        //   from	to	target	type
        //   8	14	66	finally
        //   18	29	66	finally
        //   29	49	66	finally
        //   58	63	66	finally
      }
      
      /* Error */
      public void l(d paramd)
        throws RemoteException
      {
        // Byte code:
        //   0: invokestatic 25	android/os/Parcel:obtain	()Landroid/os/Parcel;
        //   3: astore_2
        //   4: invokestatic 25	android/os/Parcel:obtain	()Landroid/os/Parcel;
        //   7: astore_3
        //   8: aload_2
        //   9: ldc 27
        //   11: invokevirtual 31	android/os/Parcel:writeInterfaceToken	(Ljava/lang/String;)V
        //   14: aload_1
        //   15: ifnull +43 -> 58
        //   18: aload_2
        //   19: iconst_1
        //   20: invokevirtual 34	android/os/Parcel:writeInt	(I)V
        //   23: aload_1
        //   24: aload_2
        //   25: iconst_0
        //   26: invokevirtual 62	com/google/android/gms/common/data/d:writeToParcel	(Landroid/os/Parcel;I)V
        //   29: aload_0
        //   30: getfield 15	com/google/android/gms/internal/ay$a$a:a	Landroid/os/IBinder;
        //   33: sipush 5012
        //   36: aload_2
        //   37: aload_3
        //   38: iconst_0
        //   39: invokeinterface 40 5 0
        //   44: pop
        //   45: aload_3
        //   46: invokevirtual 43	android/os/Parcel:readException	()V
        //   49: aload_3
        //   50: invokevirtual 46	android/os/Parcel:recycle	()V
        //   53: aload_2
        //   54: invokevirtual 46	android/os/Parcel:recycle	()V
        //   57: return
        //   58: aload_2
        //   59: iconst_0
        //   60: invokevirtual 34	android/os/Parcel:writeInt	(I)V
        //   63: goto -34 -> 29
        //   66: astore 4
        //   68: aload_3
        //   69: invokevirtual 46	android/os/Parcel:recycle	()V
        //   72: aload_2
        //   73: invokevirtual 46	android/os/Parcel:recycle	()V
        //   76: aload 4
        //   78: athrow
        // Local variable table:
        //   start	length	slot	name	signature
        //   0	79	0	this	a
        //   0	79	1	paramd	d
        //   3	70	2	localParcel1	Parcel
        //   7	62	3	localParcel2	Parcel
        //   66	11	4	localObject	Object
        // Exception table:
        //   from	to	target	type
        //   8	14	66	finally
        //   18	29	66	finally
        //   29	49	66	finally
        //   58	63	66	finally
      }
      
      /* Error */
      public void m(d paramd)
        throws RemoteException
      {
        // Byte code:
        //   0: invokestatic 25	android/os/Parcel:obtain	()Landroid/os/Parcel;
        //   3: astore_2
        //   4: invokestatic 25	android/os/Parcel:obtain	()Landroid/os/Parcel;
        //   7: astore_3
        //   8: aload_2
        //   9: ldc 27
        //   11: invokevirtual 31	android/os/Parcel:writeInterfaceToken	(Ljava/lang/String;)V
        //   14: aload_1
        //   15: ifnull +43 -> 58
        //   18: aload_2
        //   19: iconst_1
        //   20: invokevirtual 34	android/os/Parcel:writeInt	(I)V
        //   23: aload_1
        //   24: aload_2
        //   25: iconst_0
        //   26: invokevirtual 62	com/google/android/gms/common/data/d:writeToParcel	(Landroid/os/Parcel;I)V
        //   29: aload_0
        //   30: getfield 15	com/google/android/gms/internal/ay$a$a:a	Landroid/os/IBinder;
        //   33: sipush 5014
        //   36: aload_2
        //   37: aload_3
        //   38: iconst_0
        //   39: invokeinterface 40 5 0
        //   44: pop
        //   45: aload_3
        //   46: invokevirtual 43	android/os/Parcel:readException	()V
        //   49: aload_3
        //   50: invokevirtual 46	android/os/Parcel:recycle	()V
        //   53: aload_2
        //   54: invokevirtual 46	android/os/Parcel:recycle	()V
        //   57: return
        //   58: aload_2
        //   59: iconst_0
        //   60: invokevirtual 34	android/os/Parcel:writeInt	(I)V
        //   63: goto -34 -> 29
        //   66: astore 4
        //   68: aload_3
        //   69: invokevirtual 46	android/os/Parcel:recycle	()V
        //   72: aload_2
        //   73: invokevirtual 46	android/os/Parcel:recycle	()V
        //   76: aload 4
        //   78: athrow
        // Local variable table:
        //   start	length	slot	name	signature
        //   0	79	0	this	a
        //   0	79	1	paramd	d
        //   3	70	2	localParcel1	Parcel
        //   7	62	3	localParcel2	Parcel
        //   66	11	4	localObject	Object
        // Exception table:
        //   from	to	target	type
        //   8	14	66	finally
        //   18	29	66	finally
        //   29	49	66	finally
        //   58	63	66	finally
      }
      
      /* Error */
      public void n(d paramd)
        throws RemoteException
      {
        // Byte code:
        //   0: invokestatic 25	android/os/Parcel:obtain	()Landroid/os/Parcel;
        //   3: astore_2
        //   4: invokestatic 25	android/os/Parcel:obtain	()Landroid/os/Parcel;
        //   7: astore_3
        //   8: aload_2
        //   9: ldc 27
        //   11: invokevirtual 31	android/os/Parcel:writeInterfaceToken	(Ljava/lang/String;)V
        //   14: aload_1
        //   15: ifnull +43 -> 58
        //   18: aload_2
        //   19: iconst_1
        //   20: invokevirtual 34	android/os/Parcel:writeInt	(I)V
        //   23: aload_1
        //   24: aload_2
        //   25: iconst_0
        //   26: invokevirtual 62	com/google/android/gms/common/data/d:writeToParcel	(Landroid/os/Parcel;I)V
        //   29: aload_0
        //   30: getfield 15	com/google/android/gms/internal/ay$a$a:a	Landroid/os/IBinder;
        //   33: sipush 5018
        //   36: aload_2
        //   37: aload_3
        //   38: iconst_0
        //   39: invokeinterface 40 5 0
        //   44: pop
        //   45: aload_3
        //   46: invokevirtual 43	android/os/Parcel:readException	()V
        //   49: aload_3
        //   50: invokevirtual 46	android/os/Parcel:recycle	()V
        //   53: aload_2
        //   54: invokevirtual 46	android/os/Parcel:recycle	()V
        //   57: return
        //   58: aload_2
        //   59: iconst_0
        //   60: invokevirtual 34	android/os/Parcel:writeInt	(I)V
        //   63: goto -34 -> 29
        //   66: astore 4
        //   68: aload_3
        //   69: invokevirtual 46	android/os/Parcel:recycle	()V
        //   72: aload_2
        //   73: invokevirtual 46	android/os/Parcel:recycle	()V
        //   76: aload 4
        //   78: athrow
        // Local variable table:
        //   start	length	slot	name	signature
        //   0	79	0	this	a
        //   0	79	1	paramd	d
        //   3	70	2	localParcel1	Parcel
        //   7	62	3	localParcel2	Parcel
        //   66	11	4	localObject	Object
        // Exception table:
        //   from	to	target	type
        //   8	14	66	finally
        //   18	29	66	finally
        //   29	49	66	finally
        //   58	63	66	finally
      }
      
      /* Error */
      public void o(d paramd)
        throws RemoteException
      {
        // Byte code:
        //   0: invokestatic 25	android/os/Parcel:obtain	()Landroid/os/Parcel;
        //   3: astore_2
        //   4: invokestatic 25	android/os/Parcel:obtain	()Landroid/os/Parcel;
        //   7: astore_3
        //   8: aload_2
        //   9: ldc 27
        //   11: invokevirtual 31	android/os/Parcel:writeInterfaceToken	(Ljava/lang/String;)V
        //   14: aload_1
        //   15: ifnull +43 -> 58
        //   18: aload_2
        //   19: iconst_1
        //   20: invokevirtual 34	android/os/Parcel:writeInt	(I)V
        //   23: aload_1
        //   24: aload_2
        //   25: iconst_0
        //   26: invokevirtual 62	com/google/android/gms/common/data/d:writeToParcel	(Landroid/os/Parcel;I)V
        //   29: aload_0
        //   30: getfield 15	com/google/android/gms/internal/ay$a$a:a	Landroid/os/IBinder;
        //   33: sipush 5019
        //   36: aload_2
        //   37: aload_3
        //   38: iconst_0
        //   39: invokeinterface 40 5 0
        //   44: pop
        //   45: aload_3
        //   46: invokevirtual 43	android/os/Parcel:readException	()V
        //   49: aload_3
        //   50: invokevirtual 46	android/os/Parcel:recycle	()V
        //   53: aload_2
        //   54: invokevirtual 46	android/os/Parcel:recycle	()V
        //   57: return
        //   58: aload_2
        //   59: iconst_0
        //   60: invokevirtual 34	android/os/Parcel:writeInt	(I)V
        //   63: goto -34 -> 29
        //   66: astore 4
        //   68: aload_3
        //   69: invokevirtual 46	android/os/Parcel:recycle	()V
        //   72: aload_2
        //   73: invokevirtual 46	android/os/Parcel:recycle	()V
        //   76: aload 4
        //   78: athrow
        // Local variable table:
        //   start	length	slot	name	signature
        //   0	79	0	this	a
        //   0	79	1	paramd	d
        //   3	70	2	localParcel1	Parcel
        //   7	62	3	localParcel2	Parcel
        //   66	11	4	localObject	Object
        // Exception table:
        //   from	to	target	type
        //   8	14	66	finally
        //   18	29	66	finally
        //   29	49	66	finally
        //   58	63	66	finally
      }
      
      public void onAchievementUpdated(int paramInt, String paramString)
        throws RemoteException
      {
        Parcel localParcel1 = Parcel.obtain();
        Parcel localParcel2 = Parcel.obtain();
        try
        {
          localParcel1.writeInterfaceToken("com.google.android.gms.games.internal.IGamesCallbacks");
          localParcel1.writeInt(paramInt);
          localParcel1.writeString(paramString);
          this.a.transact(5003, localParcel1, localParcel2, 0);
          localParcel2.readException();
          return;
        }
        finally
        {
          localParcel2.recycle();
          localParcel1.recycle();
        }
      }
      
      public void onLeftRoom(int paramInt, String paramString)
        throws RemoteException
      {
        Parcel localParcel1 = Parcel.obtain();
        Parcel localParcel2 = Parcel.obtain();
        try
        {
          localParcel1.writeInterfaceToken("com.google.android.gms.games.internal.IGamesCallbacks");
          localParcel1.writeInt(paramInt);
          localParcel1.writeString(paramString);
          this.a.transact(5020, localParcel1, localParcel2, 0);
          localParcel2.readException();
          return;
        }
        finally
        {
          localParcel2.recycle();
          localParcel1.recycle();
        }
      }
      
      public void onP2PConnected(String paramString)
        throws RemoteException
      {
        Parcel localParcel1 = Parcel.obtain();
        Parcel localParcel2 = Parcel.obtain();
        try
        {
          localParcel1.writeInterfaceToken("com.google.android.gms.games.internal.IGamesCallbacks");
          localParcel1.writeString(paramString);
          this.a.transact(6001, localParcel1, localParcel2, 0);
          localParcel2.readException();
          return;
        }
        finally
        {
          localParcel2.recycle();
          localParcel1.recycle();
        }
      }
      
      public void onP2PDisconnected(String paramString)
        throws RemoteException
      {
        Parcel localParcel1 = Parcel.obtain();
        Parcel localParcel2 = Parcel.obtain();
        try
        {
          localParcel1.writeInterfaceToken("com.google.android.gms.games.internal.IGamesCallbacks");
          localParcel1.writeString(paramString);
          this.a.transact(6002, localParcel1, localParcel2, 0);
          localParcel2.readException();
          return;
        }
        finally
        {
          localParcel2.recycle();
          localParcel1.recycle();
        }
      }
      
      /* Error */
      public void onRealTimeMessageReceived(RealTimeMessage paramRealTimeMessage)
        throws RemoteException
      {
        // Byte code:
        //   0: invokestatic 25	android/os/Parcel:obtain	()Landroid/os/Parcel;
        //   3: astore_2
        //   4: invokestatic 25	android/os/Parcel:obtain	()Landroid/os/Parcel;
        //   7: astore_3
        //   8: aload_2
        //   9: ldc 27
        //   11: invokevirtual 31	android/os/Parcel:writeInterfaceToken	(Ljava/lang/String;)V
        //   14: aload_1
        //   15: ifnull +43 -> 58
        //   18: aload_2
        //   19: iconst_1
        //   20: invokevirtual 34	android/os/Parcel:writeInt	(I)V
        //   23: aload_1
        //   24: aload_2
        //   25: iconst_0
        //   26: invokevirtual 93	com/google/android/gms/games/multiplayer/realtime/RealTimeMessage:writeToParcel	(Landroid/os/Parcel;I)V
        //   29: aload_0
        //   30: getfield 15	com/google/android/gms/internal/ay$a$a:a	Landroid/os/IBinder;
        //   33: sipush 5032
        //   36: aload_2
        //   37: aload_3
        //   38: iconst_0
        //   39: invokeinterface 40 5 0
        //   44: pop
        //   45: aload_3
        //   46: invokevirtual 43	android/os/Parcel:readException	()V
        //   49: aload_3
        //   50: invokevirtual 46	android/os/Parcel:recycle	()V
        //   53: aload_2
        //   54: invokevirtual 46	android/os/Parcel:recycle	()V
        //   57: return
        //   58: aload_2
        //   59: iconst_0
        //   60: invokevirtual 34	android/os/Parcel:writeInt	(I)V
        //   63: goto -34 -> 29
        //   66: astore 4
        //   68: aload_3
        //   69: invokevirtual 46	android/os/Parcel:recycle	()V
        //   72: aload_2
        //   73: invokevirtual 46	android/os/Parcel:recycle	()V
        //   76: aload 4
        //   78: athrow
        // Local variable table:
        //   start	length	slot	name	signature
        //   0	79	0	this	a
        //   0	79	1	paramRealTimeMessage	RealTimeMessage
        //   3	70	2	localParcel1	Parcel
        //   7	62	3	localParcel2	Parcel
        //   66	11	4	localObject	Object
        // Exception table:
        //   from	to	target	type
        //   8	14	66	finally
        //   18	29	66	finally
        //   29	49	66	finally
        //   58	63	66	finally
      }
      
      public void onSignOutComplete()
        throws RemoteException
      {
        Parcel localParcel1 = Parcel.obtain();
        Parcel localParcel2 = Parcel.obtain();
        try
        {
          localParcel1.writeInterfaceToken("com.google.android.gms.games.internal.IGamesCallbacks");
          this.a.transact(5016, localParcel1, localParcel2, 0);
          localParcel2.readException();
          return;
        }
        finally
        {
          localParcel2.recycle();
          localParcel1.recycle();
        }
      }
      
      /* Error */
      public void p(d paramd)
        throws RemoteException
      {
        // Byte code:
        //   0: invokestatic 25	android/os/Parcel:obtain	()Landroid/os/Parcel;
        //   3: astore_2
        //   4: invokestatic 25	android/os/Parcel:obtain	()Landroid/os/Parcel;
        //   7: astore_3
        //   8: aload_2
        //   9: ldc 27
        //   11: invokevirtual 31	android/os/Parcel:writeInterfaceToken	(Ljava/lang/String;)V
        //   14: aload_1
        //   15: ifnull +43 -> 58
        //   18: aload_2
        //   19: iconst_1
        //   20: invokevirtual 34	android/os/Parcel:writeInt	(I)V
        //   23: aload_1
        //   24: aload_2
        //   25: iconst_0
        //   26: invokevirtual 62	com/google/android/gms/common/data/d:writeToParcel	(Landroid/os/Parcel;I)V
        //   29: aload_0
        //   30: getfield 15	com/google/android/gms/internal/ay$a$a:a	Landroid/os/IBinder;
        //   33: sipush 5021
        //   36: aload_2
        //   37: aload_3
        //   38: iconst_0
        //   39: invokeinterface 40 5 0
        //   44: pop
        //   45: aload_3
        //   46: invokevirtual 43	android/os/Parcel:readException	()V
        //   49: aload_3
        //   50: invokevirtual 46	android/os/Parcel:recycle	()V
        //   53: aload_2
        //   54: invokevirtual 46	android/os/Parcel:recycle	()V
        //   57: return
        //   58: aload_2
        //   59: iconst_0
        //   60: invokevirtual 34	android/os/Parcel:writeInt	(I)V
        //   63: goto -34 -> 29
        //   66: astore 4
        //   68: aload_3
        //   69: invokevirtual 46	android/os/Parcel:recycle	()V
        //   72: aload_2
        //   73: invokevirtual 46	android/os/Parcel:recycle	()V
        //   76: aload 4
        //   78: athrow
        // Local variable table:
        //   start	length	slot	name	signature
        //   0	79	0	this	a
        //   0	79	1	paramd	d
        //   3	70	2	localParcel1	Parcel
        //   7	62	3	localParcel2	Parcel
        //   66	11	4	localObject	Object
        // Exception table:
        //   from	to	target	type
        //   8	14	66	finally
        //   18	29	66	finally
        //   29	49	66	finally
        //   58	63	66	finally
      }
      
      /* Error */
      public void q(d paramd)
        throws RemoteException
      {
        // Byte code:
        //   0: invokestatic 25	android/os/Parcel:obtain	()Landroid/os/Parcel;
        //   3: astore_2
        //   4: invokestatic 25	android/os/Parcel:obtain	()Landroid/os/Parcel;
        //   7: astore_3
        //   8: aload_2
        //   9: ldc 27
        //   11: invokevirtual 31	android/os/Parcel:writeInterfaceToken	(Ljava/lang/String;)V
        //   14: aload_1
        //   15: ifnull +43 -> 58
        //   18: aload_2
        //   19: iconst_1
        //   20: invokevirtual 34	android/os/Parcel:writeInt	(I)V
        //   23: aload_1
        //   24: aload_2
        //   25: iconst_0
        //   26: invokevirtual 62	com/google/android/gms/common/data/d:writeToParcel	(Landroid/os/Parcel;I)V
        //   29: aload_0
        //   30: getfield 15	com/google/android/gms/internal/ay$a$a:a	Landroid/os/IBinder;
        //   33: sipush 5022
        //   36: aload_2
        //   37: aload_3
        //   38: iconst_0
        //   39: invokeinterface 40 5 0
        //   44: pop
        //   45: aload_3
        //   46: invokevirtual 43	android/os/Parcel:readException	()V
        //   49: aload_3
        //   50: invokevirtual 46	android/os/Parcel:recycle	()V
        //   53: aload_2
        //   54: invokevirtual 46	android/os/Parcel:recycle	()V
        //   57: return
        //   58: aload_2
        //   59: iconst_0
        //   60: invokevirtual 34	android/os/Parcel:writeInt	(I)V
        //   63: goto -34 -> 29
        //   66: astore 4
        //   68: aload_3
        //   69: invokevirtual 46	android/os/Parcel:recycle	()V
        //   72: aload_2
        //   73: invokevirtual 46	android/os/Parcel:recycle	()V
        //   76: aload 4
        //   78: athrow
        // Local variable table:
        //   start	length	slot	name	signature
        //   0	79	0	this	a
        //   0	79	1	paramd	d
        //   3	70	2	localParcel1	Parcel
        //   7	62	3	localParcel2	Parcel
        //   66	11	4	localObject	Object
        // Exception table:
        //   from	to	target	type
        //   8	14	66	finally
        //   18	29	66	finally
        //   29	49	66	finally
        //   58	63	66	finally
      }
      
      /* Error */
      public void r(d paramd)
        throws RemoteException
      {
        // Byte code:
        //   0: invokestatic 25	android/os/Parcel:obtain	()Landroid/os/Parcel;
        //   3: astore_2
        //   4: invokestatic 25	android/os/Parcel:obtain	()Landroid/os/Parcel;
        //   7: astore_3
        //   8: aload_2
        //   9: ldc 27
        //   11: invokevirtual 31	android/os/Parcel:writeInterfaceToken	(Ljava/lang/String;)V
        //   14: aload_1
        //   15: ifnull +43 -> 58
        //   18: aload_2
        //   19: iconst_1
        //   20: invokevirtual 34	android/os/Parcel:writeInt	(I)V
        //   23: aload_1
        //   24: aload_2
        //   25: iconst_0
        //   26: invokevirtual 62	com/google/android/gms/common/data/d:writeToParcel	(Landroid/os/Parcel;I)V
        //   29: aload_0
        //   30: getfield 15	com/google/android/gms/internal/ay$a$a:a	Landroid/os/IBinder;
        //   33: sipush 5023
        //   36: aload_2
        //   37: aload_3
        //   38: iconst_0
        //   39: invokeinterface 40 5 0
        //   44: pop
        //   45: aload_3
        //   46: invokevirtual 43	android/os/Parcel:readException	()V
        //   49: aload_3
        //   50: invokevirtual 46	android/os/Parcel:recycle	()V
        //   53: aload_2
        //   54: invokevirtual 46	android/os/Parcel:recycle	()V
        //   57: return
        //   58: aload_2
        //   59: iconst_0
        //   60: invokevirtual 34	android/os/Parcel:writeInt	(I)V
        //   63: goto -34 -> 29
        //   66: astore 4
        //   68: aload_3
        //   69: invokevirtual 46	android/os/Parcel:recycle	()V
        //   72: aload_2
        //   73: invokevirtual 46	android/os/Parcel:recycle	()V
        //   76: aload 4
        //   78: athrow
        // Local variable table:
        //   start	length	slot	name	signature
        //   0	79	0	this	a
        //   0	79	1	paramd	d
        //   3	70	2	localParcel1	Parcel
        //   7	62	3	localParcel2	Parcel
        //   66	11	4	localObject	Object
        // Exception table:
        //   from	to	target	type
        //   8	14	66	finally
        //   18	29	66	finally
        //   29	49	66	finally
        //   58	63	66	finally
      }
      
      /* Error */
      public void s(d paramd)
        throws RemoteException
      {
        // Byte code:
        //   0: invokestatic 25	android/os/Parcel:obtain	()Landroid/os/Parcel;
        //   3: astore_2
        //   4: invokestatic 25	android/os/Parcel:obtain	()Landroid/os/Parcel;
        //   7: astore_3
        //   8: aload_2
        //   9: ldc 27
        //   11: invokevirtual 31	android/os/Parcel:writeInterfaceToken	(Ljava/lang/String;)V
        //   14: aload_1
        //   15: ifnull +43 -> 58
        //   18: aload_2
        //   19: iconst_1
        //   20: invokevirtual 34	android/os/Parcel:writeInt	(I)V
        //   23: aload_1
        //   24: aload_2
        //   25: iconst_0
        //   26: invokevirtual 62	com/google/android/gms/common/data/d:writeToParcel	(Landroid/os/Parcel;I)V
        //   29: aload_0
        //   30: getfield 15	com/google/android/gms/internal/ay$a$a:a	Landroid/os/IBinder;
        //   33: sipush 5024
        //   36: aload_2
        //   37: aload_3
        //   38: iconst_0
        //   39: invokeinterface 40 5 0
        //   44: pop
        //   45: aload_3
        //   46: invokevirtual 43	android/os/Parcel:readException	()V
        //   49: aload_3
        //   50: invokevirtual 46	android/os/Parcel:recycle	()V
        //   53: aload_2
        //   54: invokevirtual 46	android/os/Parcel:recycle	()V
        //   57: return
        //   58: aload_2
        //   59: iconst_0
        //   60: invokevirtual 34	android/os/Parcel:writeInt	(I)V
        //   63: goto -34 -> 29
        //   66: astore 4
        //   68: aload_3
        //   69: invokevirtual 46	android/os/Parcel:recycle	()V
        //   72: aload_2
        //   73: invokevirtual 46	android/os/Parcel:recycle	()V
        //   76: aload 4
        //   78: athrow
        // Local variable table:
        //   start	length	slot	name	signature
        //   0	79	0	this	a
        //   0	79	1	paramd	d
        //   3	70	2	localParcel1	Parcel
        //   7	62	3	localParcel2	Parcel
        //   66	11	4	localObject	Object
        // Exception table:
        //   from	to	target	type
        //   8	14	66	finally
        //   18	29	66	finally
        //   29	49	66	finally
        //   58	63	66	finally
      }
      
      /* Error */
      public void t(d paramd)
        throws RemoteException
      {
        // Byte code:
        //   0: invokestatic 25	android/os/Parcel:obtain	()Landroid/os/Parcel;
        //   3: astore_2
        //   4: invokestatic 25	android/os/Parcel:obtain	()Landroid/os/Parcel;
        //   7: astore_3
        //   8: aload_2
        //   9: ldc 27
        //   11: invokevirtual 31	android/os/Parcel:writeInterfaceToken	(Ljava/lang/String;)V
        //   14: aload_1
        //   15: ifnull +43 -> 58
        //   18: aload_2
        //   19: iconst_1
        //   20: invokevirtual 34	android/os/Parcel:writeInt	(I)V
        //   23: aload_1
        //   24: aload_2
        //   25: iconst_0
        //   26: invokevirtual 62	com/google/android/gms/common/data/d:writeToParcel	(Landroid/os/Parcel;I)V
        //   29: aload_0
        //   30: getfield 15	com/google/android/gms/internal/ay$a$a:a	Landroid/os/IBinder;
        //   33: sipush 5025
        //   36: aload_2
        //   37: aload_3
        //   38: iconst_0
        //   39: invokeinterface 40 5 0
        //   44: pop
        //   45: aload_3
        //   46: invokevirtual 43	android/os/Parcel:readException	()V
        //   49: aload_3
        //   50: invokevirtual 46	android/os/Parcel:recycle	()V
        //   53: aload_2
        //   54: invokevirtual 46	android/os/Parcel:recycle	()V
        //   57: return
        //   58: aload_2
        //   59: iconst_0
        //   60: invokevirtual 34	android/os/Parcel:writeInt	(I)V
        //   63: goto -34 -> 29
        //   66: astore 4
        //   68: aload_3
        //   69: invokevirtual 46	android/os/Parcel:recycle	()V
        //   72: aload_2
        //   73: invokevirtual 46	android/os/Parcel:recycle	()V
        //   76: aload 4
        //   78: athrow
        // Local variable table:
        //   start	length	slot	name	signature
        //   0	79	0	this	a
        //   0	79	1	paramd	d
        //   3	70	2	localParcel1	Parcel
        //   7	62	3	localParcel2	Parcel
        //   66	11	4	localObject	Object
        // Exception table:
        //   from	to	target	type
        //   8	14	66	finally
        //   18	29	66	finally
        //   29	49	66	finally
        //   58	63	66	finally
      }
      
      /* Error */
      public void u(d paramd)
        throws RemoteException
      {
        // Byte code:
        //   0: invokestatic 25	android/os/Parcel:obtain	()Landroid/os/Parcel;
        //   3: astore_2
        //   4: invokestatic 25	android/os/Parcel:obtain	()Landroid/os/Parcel;
        //   7: astore_3
        //   8: aload_2
        //   9: ldc 27
        //   11: invokevirtual 31	android/os/Parcel:writeInterfaceToken	(Ljava/lang/String;)V
        //   14: aload_1
        //   15: ifnull +43 -> 58
        //   18: aload_2
        //   19: iconst_1
        //   20: invokevirtual 34	android/os/Parcel:writeInt	(I)V
        //   23: aload_1
        //   24: aload_2
        //   25: iconst_0
        //   26: invokevirtual 62	com/google/android/gms/common/data/d:writeToParcel	(Landroid/os/Parcel;I)V
        //   29: aload_0
        //   30: getfield 15	com/google/android/gms/internal/ay$a$a:a	Landroid/os/IBinder;
        //   33: sipush 5038
        //   36: aload_2
        //   37: aload_3
        //   38: iconst_0
        //   39: invokeinterface 40 5 0
        //   44: pop
        //   45: aload_3
        //   46: invokevirtual 43	android/os/Parcel:readException	()V
        //   49: aload_3
        //   50: invokevirtual 46	android/os/Parcel:recycle	()V
        //   53: aload_2
        //   54: invokevirtual 46	android/os/Parcel:recycle	()V
        //   57: return
        //   58: aload_2
        //   59: iconst_0
        //   60: invokevirtual 34	android/os/Parcel:writeInt	(I)V
        //   63: goto -34 -> 29
        //   66: astore 4
        //   68: aload_3
        //   69: invokevirtual 46	android/os/Parcel:recycle	()V
        //   72: aload_2
        //   73: invokevirtual 46	android/os/Parcel:recycle	()V
        //   76: aload 4
        //   78: athrow
        // Local variable table:
        //   start	length	slot	name	signature
        //   0	79	0	this	a
        //   0	79	1	paramd	d
        //   3	70	2	localParcel1	Parcel
        //   7	62	3	localParcel2	Parcel
        //   66	11	4	localObject	Object
        // Exception table:
        //   from	to	target	type
        //   8	14	66	finally
        //   18	29	66	finally
        //   29	49	66	finally
        //   58	63	66	finally
      }
      
      /* Error */
      public void v(d paramd)
        throws RemoteException
      {
        // Byte code:
        //   0: invokestatic 25	android/os/Parcel:obtain	()Landroid/os/Parcel;
        //   3: astore_2
        //   4: invokestatic 25	android/os/Parcel:obtain	()Landroid/os/Parcel;
        //   7: astore_3
        //   8: aload_2
        //   9: ldc 27
        //   11: invokevirtual 31	android/os/Parcel:writeInterfaceToken	(Ljava/lang/String;)V
        //   14: aload_1
        //   15: ifnull +43 -> 58
        //   18: aload_2
        //   19: iconst_1
        //   20: invokevirtual 34	android/os/Parcel:writeInt	(I)V
        //   23: aload_1
        //   24: aload_2
        //   25: iconst_0
        //   26: invokevirtual 62	com/google/android/gms/common/data/d:writeToParcel	(Landroid/os/Parcel;I)V
        //   29: aload_0
        //   30: getfield 15	com/google/android/gms/internal/ay$a$a:a	Landroid/os/IBinder;
        //   33: sipush 5035
        //   36: aload_2
        //   37: aload_3
        //   38: iconst_0
        //   39: invokeinterface 40 5 0
        //   44: pop
        //   45: aload_3
        //   46: invokevirtual 43	android/os/Parcel:readException	()V
        //   49: aload_3
        //   50: invokevirtual 46	android/os/Parcel:recycle	()V
        //   53: aload_2
        //   54: invokevirtual 46	android/os/Parcel:recycle	()V
        //   57: return
        //   58: aload_2
        //   59: iconst_0
        //   60: invokevirtual 34	android/os/Parcel:writeInt	(I)V
        //   63: goto -34 -> 29
        //   66: astore 4
        //   68: aload_3
        //   69: invokevirtual 46	android/os/Parcel:recycle	()V
        //   72: aload_2
        //   73: invokevirtual 46	android/os/Parcel:recycle	()V
        //   76: aload 4
        //   78: athrow
        // Local variable table:
        //   start	length	slot	name	signature
        //   0	79	0	this	a
        //   0	79	1	paramd	d
        //   3	70	2	localParcel1	Parcel
        //   7	62	3	localParcel2	Parcel
        //   66	11	4	localObject	Object
        // Exception table:
        //   from	to	target	type
        //   8	14	66	finally
        //   18	29	66	finally
        //   29	49	66	finally
        //   58	63	66	finally
      }
      
      /* Error */
      public void w(d paramd)
        throws RemoteException
      {
        // Byte code:
        //   0: invokestatic 25	android/os/Parcel:obtain	()Landroid/os/Parcel;
        //   3: astore_2
        //   4: invokestatic 25	android/os/Parcel:obtain	()Landroid/os/Parcel;
        //   7: astore_3
        //   8: aload_2
        //   9: ldc 27
        //   11: invokevirtual 31	android/os/Parcel:writeInterfaceToken	(Ljava/lang/String;)V
        //   14: aload_1
        //   15: ifnull +43 -> 58
        //   18: aload_2
        //   19: iconst_1
        //   20: invokevirtual 34	android/os/Parcel:writeInt	(I)V
        //   23: aload_1
        //   24: aload_2
        //   25: iconst_0
        //   26: invokevirtual 62	com/google/android/gms/common/data/d:writeToParcel	(Landroid/os/Parcel;I)V
        //   29: aload_0
        //   30: getfield 15	com/google/android/gms/internal/ay$a$a:a	Landroid/os/IBinder;
        //   33: sipush 5039
        //   36: aload_2
        //   37: aload_3
        //   38: iconst_0
        //   39: invokeinterface 40 5 0
        //   44: pop
        //   45: aload_3
        //   46: invokevirtual 43	android/os/Parcel:readException	()V
        //   49: aload_3
        //   50: invokevirtual 46	android/os/Parcel:recycle	()V
        //   53: aload_2
        //   54: invokevirtual 46	android/os/Parcel:recycle	()V
        //   57: return
        //   58: aload_2
        //   59: iconst_0
        //   60: invokevirtual 34	android/os/Parcel:writeInt	(I)V
        //   63: goto -34 -> 29
        //   66: astore 4
        //   68: aload_3
        //   69: invokevirtual 46	android/os/Parcel:recycle	()V
        //   72: aload_2
        //   73: invokevirtual 46	android/os/Parcel:recycle	()V
        //   76: aload 4
        //   78: athrow
        // Local variable table:
        //   start	length	slot	name	signature
        //   0	79	0	this	a
        //   0	79	1	paramd	d
        //   3	70	2	localParcel1	Parcel
        //   7	62	3	localParcel2	Parcel
        //   66	11	4	localObject	Object
        // Exception table:
        //   from	to	target	type
        //   8	14	66	finally
        //   18	29	66	finally
        //   29	49	66	finally
        //   58	63	66	finally
      }
    }
  }
}


/* Location:              /root/Documents/wemo_apk/classes-dex2jar.jar!/com/google/android/gms/internal/ay.class
 * Java compiler version: 6 (50.0)
 * JD-Core Version:       0.7.1
 */