package com.google.android.gms.internal;

import android.app.PendingIntent;
import android.os.Binder;
import android.os.IBinder;
import android.os.IInterface;
import android.os.Parcel;
import android.os.Parcelable.Creator;
import android.os.RemoteException;

public abstract interface be
  extends IInterface
{
  public abstract void onAddGeofencesResult(int paramInt, String[] paramArrayOfString)
    throws RemoteException;
  
  public abstract void onRemoveGeofencesByPendingIntentResult(int paramInt, PendingIntent paramPendingIntent)
    throws RemoteException;
  
  public abstract void onRemoveGeofencesByRequestIdsResult(int paramInt, String[] paramArrayOfString)
    throws RemoteException;
  
  public static abstract class a
    extends Binder
    implements be
  {
    public a()
    {
      attachInterface(this, "com.google.android.gms.location.internal.IGeofencerCallbacks");
    }
    
    public static be q(IBinder paramIBinder)
    {
      if (paramIBinder == null) {
        return null;
      }
      IInterface localIInterface = paramIBinder.queryLocalInterface("com.google.android.gms.location.internal.IGeofencerCallbacks");
      if ((localIInterface != null) && ((localIInterface instanceof be))) {
        return (be)localIInterface;
      }
      return new a(paramIBinder);
    }
    
    public IBinder asBinder()
    {
      return this;
    }
    
    public boolean onTransact(int paramInt1, Parcel paramParcel1, Parcel paramParcel2, int paramInt2)
      throws RemoteException
    {
      switch (paramInt1)
      {
      default: 
        return super.onTransact(paramInt1, paramParcel1, paramParcel2, paramInt2);
      case 1598968902: 
        paramParcel2.writeString("com.google.android.gms.location.internal.IGeofencerCallbacks");
        return true;
      case 1: 
        paramParcel1.enforceInterface("com.google.android.gms.location.internal.IGeofencerCallbacks");
        onAddGeofencesResult(paramParcel1.readInt(), paramParcel1.createStringArray());
        paramParcel2.writeNoException();
        return true;
      case 2: 
        paramParcel1.enforceInterface("com.google.android.gms.location.internal.IGeofencerCallbacks");
        onRemoveGeofencesByRequestIdsResult(paramParcel1.readInt(), paramParcel1.createStringArray());
        paramParcel2.writeNoException();
        return true;
      }
      paramParcel1.enforceInterface("com.google.android.gms.location.internal.IGeofencerCallbacks");
      int i = paramParcel1.readInt();
      if (paramParcel1.readInt() != 0) {}
      for (PendingIntent localPendingIntent = (PendingIntent)PendingIntent.CREATOR.createFromParcel(paramParcel1);; localPendingIntent = null)
      {
        onRemoveGeofencesByPendingIntentResult(i, localPendingIntent);
        paramParcel2.writeNoException();
        return true;
      }
    }
    
    private static class a
      implements be
    {
      private IBinder a;
      
      a(IBinder paramIBinder)
      {
        this.a = paramIBinder;
      }
      
      public IBinder asBinder()
      {
        return this.a;
      }
      
      public void onAddGeofencesResult(int paramInt, String[] paramArrayOfString)
        throws RemoteException
      {
        Parcel localParcel1 = Parcel.obtain();
        Parcel localParcel2 = Parcel.obtain();
        try
        {
          localParcel1.writeInterfaceToken("com.google.android.gms.location.internal.IGeofencerCallbacks");
          localParcel1.writeInt(paramInt);
          localParcel1.writeStringArray(paramArrayOfString);
          this.a.transact(1, localParcel1, localParcel2, 0);
          localParcel2.readException();
          return;
        }
        finally
        {
          localParcel2.recycle();
          localParcel1.recycle();
        }
      }
      
      /* Error */
      public void onRemoveGeofencesByPendingIntentResult(int paramInt, PendingIntent paramPendingIntent)
        throws RemoteException
      {
        // Byte code:
        //   0: invokestatic 27	android/os/Parcel:obtain	()Landroid/os/Parcel;
        //   3: astore_3
        //   4: invokestatic 27	android/os/Parcel:obtain	()Landroid/os/Parcel;
        //   7: astore 4
        //   9: aload_3
        //   10: ldc 29
        //   12: invokevirtual 33	android/os/Parcel:writeInterfaceToken	(Ljava/lang/String;)V
        //   15: aload_3
        //   16: iload_1
        //   17: invokevirtual 37	android/os/Parcel:writeInt	(I)V
        //   20: aload_2
        //   21: ifnull +44 -> 65
        //   24: aload_3
        //   25: iconst_1
        //   26: invokevirtual 37	android/os/Parcel:writeInt	(I)V
        //   29: aload_2
        //   30: aload_3
        //   31: iconst_0
        //   32: invokevirtual 61	android/app/PendingIntent:writeToParcel	(Landroid/os/Parcel;I)V
        //   35: aload_0
        //   36: getfield 15	com/google/android/gms/internal/be$a$a:a	Landroid/os/IBinder;
        //   39: iconst_3
        //   40: aload_3
        //   41: aload 4
        //   43: iconst_0
        //   44: invokeinterface 47 5 0
        //   49: pop
        //   50: aload 4
        //   52: invokevirtual 50	android/os/Parcel:readException	()V
        //   55: aload 4
        //   57: invokevirtual 53	android/os/Parcel:recycle	()V
        //   60: aload_3
        //   61: invokevirtual 53	android/os/Parcel:recycle	()V
        //   64: return
        //   65: aload_3
        //   66: iconst_0
        //   67: invokevirtual 37	android/os/Parcel:writeInt	(I)V
        //   70: goto -35 -> 35
        //   73: astore 5
        //   75: aload 4
        //   77: invokevirtual 53	android/os/Parcel:recycle	()V
        //   80: aload_3
        //   81: invokevirtual 53	android/os/Parcel:recycle	()V
        //   84: aload 5
        //   86: athrow
        // Local variable table:
        //   start	length	slot	name	signature
        //   0	87	0	this	a
        //   0	87	1	paramInt	int
        //   0	87	2	paramPendingIntent	PendingIntent
        //   3	78	3	localParcel1	Parcel
        //   7	69	4	localParcel2	Parcel
        //   73	12	5	localObject	Object
        // Exception table:
        //   from	to	target	type
        //   9	20	73	finally
        //   24	35	73	finally
        //   35	55	73	finally
        //   65	70	73	finally
      }
      
      public void onRemoveGeofencesByRequestIdsResult(int paramInt, String[] paramArrayOfString)
        throws RemoteException
      {
        Parcel localParcel1 = Parcel.obtain();
        Parcel localParcel2 = Parcel.obtain();
        try
        {
          localParcel1.writeInterfaceToken("com.google.android.gms.location.internal.IGeofencerCallbacks");
          localParcel1.writeInt(paramInt);
          localParcel1.writeStringArray(paramArrayOfString);
          this.a.transact(2, localParcel1, localParcel2, 0);
          localParcel2.readException();
          return;
        }
        finally
        {
          localParcel2.recycle();
          localParcel1.recycle();
        }
      }
    }
  }
}


/* Location:              /root/Documents/wemo_apk/classes-dex2jar.jar!/com/google/android/gms/internal/be.class
 * Java compiler version: 6 (50.0)
 * JD-Core Version:       0.7.1
 */