package com.google.android.gms.maps.model.internal;

import android.graphics.Bitmap;
import android.os.Binder;
import android.os.IBinder;
import android.os.IInterface;
import android.os.Parcel;
import android.os.Parcelable.Creator;
import android.os.RemoteException;
import com.google.android.gms.dynamic.b;
import com.google.android.gms.dynamic.b.a;

public abstract interface a
  extends IInterface
{
  public abstract b B(String paramString)
    throws RemoteException;
  
  public abstract b C(String paramString)
    throws RemoteException;
  
  public abstract b D(String paramString)
    throws RemoteException;
  
  public abstract b S(int paramInt)
    throws RemoteException;
  
  public abstract b a(Bitmap paramBitmap)
    throws RemoteException;
  
  public abstract b bt()
    throws RemoteException;
  
  public abstract b c(float paramFloat)
    throws RemoteException;
  
  public static abstract class a
    extends Binder
    implements a
  {
    public static a N(IBinder paramIBinder)
    {
      if (paramIBinder == null) {
        return null;
      }
      IInterface localIInterface = paramIBinder.queryLocalInterface("com.google.android.gms.maps.model.internal.IBitmapDescriptorFactoryDelegate");
      if ((localIInterface != null) && ((localIInterface instanceof a))) {
        return (a)localIInterface;
      }
      return new a(paramIBinder);
    }
    
    public boolean onTransact(int paramInt1, Parcel paramParcel1, Parcel paramParcel2, int paramInt2)
      throws RemoteException
    {
      switch (paramInt1)
      {
      default: 
        return super.onTransact(paramInt1, paramParcel1, paramParcel2, paramInt2);
      case 1598968902: 
        paramParcel2.writeString("com.google.android.gms.maps.model.internal.IBitmapDescriptorFactoryDelegate");
        return true;
      case 1: 
        paramParcel1.enforceInterface("com.google.android.gms.maps.model.internal.IBitmapDescriptorFactoryDelegate");
        b localb7 = S(paramParcel1.readInt());
        paramParcel2.writeNoException();
        if (localb7 != null) {}
        for (IBinder localIBinder7 = localb7.asBinder();; localIBinder7 = null)
        {
          paramParcel2.writeStrongBinder(localIBinder7);
          return true;
        }
      case 2: 
        paramParcel1.enforceInterface("com.google.android.gms.maps.model.internal.IBitmapDescriptorFactoryDelegate");
        b localb6 = B(paramParcel1.readString());
        paramParcel2.writeNoException();
        IBinder localIBinder6 = null;
        if (localb6 != null) {
          localIBinder6 = localb6.asBinder();
        }
        paramParcel2.writeStrongBinder(localIBinder6);
        return true;
      case 3: 
        paramParcel1.enforceInterface("com.google.android.gms.maps.model.internal.IBitmapDescriptorFactoryDelegate");
        b localb5 = C(paramParcel1.readString());
        paramParcel2.writeNoException();
        IBinder localIBinder5 = null;
        if (localb5 != null) {
          localIBinder5 = localb5.asBinder();
        }
        paramParcel2.writeStrongBinder(localIBinder5);
        return true;
      case 4: 
        paramParcel1.enforceInterface("com.google.android.gms.maps.model.internal.IBitmapDescriptorFactoryDelegate");
        b localb4 = bt();
        paramParcel2.writeNoException();
        IBinder localIBinder4 = null;
        if (localb4 != null) {
          localIBinder4 = localb4.asBinder();
        }
        paramParcel2.writeStrongBinder(localIBinder4);
        return true;
      case 5: 
        paramParcel1.enforceInterface("com.google.android.gms.maps.model.internal.IBitmapDescriptorFactoryDelegate");
        b localb3 = c(paramParcel1.readFloat());
        paramParcel2.writeNoException();
        IBinder localIBinder3 = null;
        if (localb3 != null) {
          localIBinder3 = localb3.asBinder();
        }
        paramParcel2.writeStrongBinder(localIBinder3);
        return true;
      case 6: 
        paramParcel1.enforceInterface("com.google.android.gms.maps.model.internal.IBitmapDescriptorFactoryDelegate");
        if (paramParcel1.readInt() != 0) {}
        for (Bitmap localBitmap = (Bitmap)Bitmap.CREATOR.createFromParcel(paramParcel1);; localBitmap = null)
        {
          b localb2 = a(localBitmap);
          paramParcel2.writeNoException();
          IBinder localIBinder2 = null;
          if (localb2 != null) {
            localIBinder2 = localb2.asBinder();
          }
          paramParcel2.writeStrongBinder(localIBinder2);
          return true;
        }
      }
      paramParcel1.enforceInterface("com.google.android.gms.maps.model.internal.IBitmapDescriptorFactoryDelegate");
      b localb1 = D(paramParcel1.readString());
      paramParcel2.writeNoException();
      IBinder localIBinder1 = null;
      if (localb1 != null) {
        localIBinder1 = localb1.asBinder();
      }
      paramParcel2.writeStrongBinder(localIBinder1);
      return true;
    }
    
    private static class a
      implements a
    {
      private IBinder a;
      
      a(IBinder paramIBinder)
      {
        this.a = paramIBinder;
      }
      
      public b B(String paramString)
        throws RemoteException
      {
        Parcel localParcel1 = Parcel.obtain();
        Parcel localParcel2 = Parcel.obtain();
        try
        {
          localParcel1.writeInterfaceToken("com.google.android.gms.maps.model.internal.IBitmapDescriptorFactoryDelegate");
          localParcel1.writeString(paramString);
          this.a.transact(2, localParcel1, localParcel2, 0);
          localParcel2.readException();
          b localb = b.a.l(localParcel2.readStrongBinder());
          return localb;
        }
        finally
        {
          localParcel2.recycle();
          localParcel1.recycle();
        }
      }
      
      public b C(String paramString)
        throws RemoteException
      {
        Parcel localParcel1 = Parcel.obtain();
        Parcel localParcel2 = Parcel.obtain();
        try
        {
          localParcel1.writeInterfaceToken("com.google.android.gms.maps.model.internal.IBitmapDescriptorFactoryDelegate");
          localParcel1.writeString(paramString);
          this.a.transact(3, localParcel1, localParcel2, 0);
          localParcel2.readException();
          b localb = b.a.l(localParcel2.readStrongBinder());
          return localb;
        }
        finally
        {
          localParcel2.recycle();
          localParcel1.recycle();
        }
      }
      
      public b D(String paramString)
        throws RemoteException
      {
        Parcel localParcel1 = Parcel.obtain();
        Parcel localParcel2 = Parcel.obtain();
        try
        {
          localParcel1.writeInterfaceToken("com.google.android.gms.maps.model.internal.IBitmapDescriptorFactoryDelegate");
          localParcel1.writeString(paramString);
          this.a.transact(7, localParcel1, localParcel2, 0);
          localParcel2.readException();
          b localb = b.a.l(localParcel2.readStrongBinder());
          return localb;
        }
        finally
        {
          localParcel2.recycle();
          localParcel1.recycle();
        }
      }
      
      public b S(int paramInt)
        throws RemoteException
      {
        Parcel localParcel1 = Parcel.obtain();
        Parcel localParcel2 = Parcel.obtain();
        try
        {
          localParcel1.writeInterfaceToken("com.google.android.gms.maps.model.internal.IBitmapDescriptorFactoryDelegate");
          localParcel1.writeInt(paramInt);
          this.a.transact(1, localParcel1, localParcel2, 0);
          localParcel2.readException();
          b localb = b.a.l(localParcel2.readStrongBinder());
          return localb;
        }
        finally
        {
          localParcel2.recycle();
          localParcel1.recycle();
        }
      }
      
      /* Error */
      public b a(Bitmap paramBitmap)
        throws RemoteException
      {
        // Byte code:
        //   0: invokestatic 25	android/os/Parcel:obtain	()Landroid/os/Parcel;
        //   3: astore_2
        //   4: invokestatic 25	android/os/Parcel:obtain	()Landroid/os/Parcel;
        //   7: astore_3
        //   8: aload_2
        //   9: ldc 27
        //   11: invokevirtual 31	android/os/Parcel:writeInterfaceToken	(Ljava/lang/String;)V
        //   14: aload_1
        //   15: ifnull +53 -> 68
        //   18: aload_2
        //   19: iconst_1
        //   20: invokevirtual 64	android/os/Parcel:writeInt	(I)V
        //   23: aload_1
        //   24: aload_2
        //   25: iconst_0
        //   26: invokevirtual 71	android/graphics/Bitmap:writeToParcel	(Landroid/os/Parcel;I)V
        //   29: aload_0
        //   30: getfield 15	com/google/android/gms/maps/model/internal/a$a$a:a	Landroid/os/IBinder;
        //   33: bipush 6
        //   35: aload_2
        //   36: aload_3
        //   37: iconst_0
        //   38: invokeinterface 40 5 0
        //   43: pop
        //   44: aload_3
        //   45: invokevirtual 43	android/os/Parcel:readException	()V
        //   48: aload_3
        //   49: invokevirtual 47	android/os/Parcel:readStrongBinder	()Landroid/os/IBinder;
        //   52: invokestatic 53	com/google/android/gms/dynamic/b$a:l	(Landroid/os/IBinder;)Lcom/google/android/gms/dynamic/b;
        //   55: astore 6
        //   57: aload_3
        //   58: invokevirtual 56	android/os/Parcel:recycle	()V
        //   61: aload_2
        //   62: invokevirtual 56	android/os/Parcel:recycle	()V
        //   65: aload 6
        //   67: areturn
        //   68: aload_2
        //   69: iconst_0
        //   70: invokevirtual 64	android/os/Parcel:writeInt	(I)V
        //   73: goto -44 -> 29
        //   76: astore 4
        //   78: aload_3
        //   79: invokevirtual 56	android/os/Parcel:recycle	()V
        //   82: aload_2
        //   83: invokevirtual 56	android/os/Parcel:recycle	()V
        //   86: aload 4
        //   88: athrow
        // Local variable table:
        //   start	length	slot	name	signature
        //   0	89	0	this	a
        //   0	89	1	paramBitmap	Bitmap
        //   3	80	2	localParcel1	Parcel
        //   7	72	3	localParcel2	Parcel
        //   76	11	4	localObject	Object
        //   55	11	6	localb	b
        // Exception table:
        //   from	to	target	type
        //   8	14	76	finally
        //   18	29	76	finally
        //   29	57	76	finally
        //   68	73	76	finally
      }
      
      public IBinder asBinder()
      {
        return this.a;
      }
      
      public b bt()
        throws RemoteException
      {
        Parcel localParcel1 = Parcel.obtain();
        Parcel localParcel2 = Parcel.obtain();
        try
        {
          localParcel1.writeInterfaceToken("com.google.android.gms.maps.model.internal.IBitmapDescriptorFactoryDelegate");
          this.a.transact(4, localParcel1, localParcel2, 0);
          localParcel2.readException();
          b localb = b.a.l(localParcel2.readStrongBinder());
          return localb;
        }
        finally
        {
          localParcel2.recycle();
          localParcel1.recycle();
        }
      }
      
      public b c(float paramFloat)
        throws RemoteException
      {
        Parcel localParcel1 = Parcel.obtain();
        Parcel localParcel2 = Parcel.obtain();
        try
        {
          localParcel1.writeInterfaceToken("com.google.android.gms.maps.model.internal.IBitmapDescriptorFactoryDelegate");
          localParcel1.writeFloat(paramFloat);
          this.a.transact(5, localParcel1, localParcel2, 0);
          localParcel2.readException();
          b localb = b.a.l(localParcel2.readStrongBinder());
          return localb;
        }
        finally
        {
          localParcel2.recycle();
          localParcel1.recycle();
        }
      }
    }
  }
}


/* Location:              /root/Documents/wemo_apk/classes-dex2jar.jar!/com/google/android/gms/maps/model/internal/a.class
 * Java compiler version: 6 (50.0)
 * JD-Core Version:       0.7.1
 */