package com.google.android.gms.maps.model.internal;

import android.os.Binder;
import android.os.IBinder;
import android.os.IInterface;
import android.os.Parcel;
import android.os.RemoteException;
import com.google.android.gms.maps.model.LatLng;
import com.google.android.gms.maps.model.LatLngCreator;

public abstract interface b
  extends IInterface
{
  public abstract boolean a(b paramb)
    throws RemoteException;
  
  public abstract LatLng getCenter()
    throws RemoteException;
  
  public abstract int getFillColor()
    throws RemoteException;
  
  public abstract String getId()
    throws RemoteException;
  
  public abstract double getRadius()
    throws RemoteException;
  
  public abstract int getStrokeColor()
    throws RemoteException;
  
  public abstract float getStrokeWidth()
    throws RemoteException;
  
  public abstract float getZIndex()
    throws RemoteException;
  
  public abstract int hashCodeRemote()
    throws RemoteException;
  
  public abstract boolean isVisible()
    throws RemoteException;
  
  public abstract void remove()
    throws RemoteException;
  
  public abstract void setCenter(LatLng paramLatLng)
    throws RemoteException;
  
  public abstract void setFillColor(int paramInt)
    throws RemoteException;
  
  public abstract void setRadius(double paramDouble)
    throws RemoteException;
  
  public abstract void setStrokeColor(int paramInt)
    throws RemoteException;
  
  public abstract void setStrokeWidth(float paramFloat)
    throws RemoteException;
  
  public abstract void setVisible(boolean paramBoolean)
    throws RemoteException;
  
  public abstract void setZIndex(float paramFloat)
    throws RemoteException;
  
  public static abstract class a
    extends Binder
    implements b
  {
    public static b O(IBinder paramIBinder)
    {
      if (paramIBinder == null) {
        return null;
      }
      IInterface localIInterface = paramIBinder.queryLocalInterface("com.google.android.gms.maps.model.internal.ICircleDelegate");
      if ((localIInterface != null) && ((localIInterface instanceof b))) {
        return (b)localIInterface;
      }
      return new a(paramIBinder);
    }
    
    public boolean onTransact(int paramInt1, Parcel paramParcel1, Parcel paramParcel2, int paramInt2)
      throws RemoteException
    {
      switch (paramInt1)
      {
      default: 
        return super.onTransact(paramInt1, paramParcel1, paramParcel2, paramInt2);
      case 1598968902: 
        paramParcel2.writeString("com.google.android.gms.maps.model.internal.ICircleDelegate");
        return true;
      case 1: 
        paramParcel1.enforceInterface("com.google.android.gms.maps.model.internal.ICircleDelegate");
        remove();
        paramParcel2.writeNoException();
        return true;
      case 2: 
        paramParcel1.enforceInterface("com.google.android.gms.maps.model.internal.ICircleDelegate");
        String str = getId();
        paramParcel2.writeNoException();
        paramParcel2.writeString(str);
        return true;
      case 3: 
        paramParcel1.enforceInterface("com.google.android.gms.maps.model.internal.ICircleDelegate");
        if (paramParcel1.readInt() != 0) {}
        for (LatLng localLatLng2 = LatLng.CREATOR.createFromParcel(paramParcel1);; localLatLng2 = null)
        {
          setCenter(localLatLng2);
          paramParcel2.writeNoException();
          return true;
        }
      case 4: 
        paramParcel1.enforceInterface("com.google.android.gms.maps.model.internal.ICircleDelegate");
        LatLng localLatLng1 = getCenter();
        paramParcel2.writeNoException();
        if (localLatLng1 != null)
        {
          paramParcel2.writeInt(1);
          localLatLng1.writeToParcel(paramParcel2, 1);
          return true;
        }
        paramParcel2.writeInt(0);
        return true;
      case 5: 
        paramParcel1.enforceInterface("com.google.android.gms.maps.model.internal.ICircleDelegate");
        setRadius(paramParcel1.readDouble());
        paramParcel2.writeNoException();
        return true;
      case 6: 
        paramParcel1.enforceInterface("com.google.android.gms.maps.model.internal.ICircleDelegate");
        double d = getRadius();
        paramParcel2.writeNoException();
        paramParcel2.writeDouble(d);
        return true;
      case 7: 
        paramParcel1.enforceInterface("com.google.android.gms.maps.model.internal.ICircleDelegate");
        setStrokeWidth(paramParcel1.readFloat());
        paramParcel2.writeNoException();
        return true;
      case 8: 
        paramParcel1.enforceInterface("com.google.android.gms.maps.model.internal.ICircleDelegate");
        float f2 = getStrokeWidth();
        paramParcel2.writeNoException();
        paramParcel2.writeFloat(f2);
        return true;
      case 9: 
        paramParcel1.enforceInterface("com.google.android.gms.maps.model.internal.ICircleDelegate");
        setStrokeColor(paramParcel1.readInt());
        paramParcel2.writeNoException();
        return true;
      case 10: 
        paramParcel1.enforceInterface("com.google.android.gms.maps.model.internal.ICircleDelegate");
        int i1 = getStrokeColor();
        paramParcel2.writeNoException();
        paramParcel2.writeInt(i1);
        return true;
      case 11: 
        paramParcel1.enforceInterface("com.google.android.gms.maps.model.internal.ICircleDelegate");
        setFillColor(paramParcel1.readInt());
        paramParcel2.writeNoException();
        return true;
      case 12: 
        paramParcel1.enforceInterface("com.google.android.gms.maps.model.internal.ICircleDelegate");
        int n = getFillColor();
        paramParcel2.writeNoException();
        paramParcel2.writeInt(n);
        return true;
      case 13: 
        paramParcel1.enforceInterface("com.google.android.gms.maps.model.internal.ICircleDelegate");
        setZIndex(paramParcel1.readFloat());
        paramParcel2.writeNoException();
        return true;
      case 14: 
        paramParcel1.enforceInterface("com.google.android.gms.maps.model.internal.ICircleDelegate");
        float f1 = getZIndex();
        paramParcel2.writeNoException();
        paramParcel2.writeFloat(f1);
        return true;
      case 15: 
        paramParcel1.enforceInterface("com.google.android.gms.maps.model.internal.ICircleDelegate");
        int m = paramParcel1.readInt();
        boolean bool3 = false;
        if (m != 0) {
          bool3 = true;
        }
        setVisible(bool3);
        paramParcel2.writeNoException();
        return true;
      case 16: 
        paramParcel1.enforceInterface("com.google.android.gms.maps.model.internal.ICircleDelegate");
        boolean bool2 = isVisible();
        paramParcel2.writeNoException();
        int k = 0;
        if (bool2) {
          k = 1;
        }
        paramParcel2.writeInt(k);
        return true;
      case 17: 
        paramParcel1.enforceInterface("com.google.android.gms.maps.model.internal.ICircleDelegate");
        boolean bool1 = a(O(paramParcel1.readStrongBinder()));
        paramParcel2.writeNoException();
        int j = 0;
        if (bool1) {
          j = 1;
        }
        paramParcel2.writeInt(j);
        return true;
      }
      paramParcel1.enforceInterface("com.google.android.gms.maps.model.internal.ICircleDelegate");
      int i = hashCodeRemote();
      paramParcel2.writeNoException();
      paramParcel2.writeInt(i);
      return true;
    }
    
    private static class a
      implements b
    {
      private IBinder a;
      
      a(IBinder paramIBinder)
      {
        this.a = paramIBinder;
      }
      
      /* Error */
      public boolean a(b paramb)
        throws RemoteException
      {
        // Byte code:
        //   0: invokestatic 24	android/os/Parcel:obtain	()Landroid/os/Parcel;
        //   3: astore_2
        //   4: invokestatic 24	android/os/Parcel:obtain	()Landroid/os/Parcel;
        //   7: astore_3
        //   8: aload_2
        //   9: ldc 26
        //   11: invokevirtual 30	android/os/Parcel:writeInterfaceToken	(Ljava/lang/String;)V
        //   14: aload_1
        //   15: ifnull +64 -> 79
        //   18: aload_1
        //   19: invokeinterface 34 1 0
        //   24: astore 5
        //   26: aload_2
        //   27: aload 5
        //   29: invokevirtual 37	android/os/Parcel:writeStrongBinder	(Landroid/os/IBinder;)V
        //   32: aload_0
        //   33: getfield 15	com/google/android/gms/maps/model/internal/b$a$a:a	Landroid/os/IBinder;
        //   36: bipush 17
        //   38: aload_2
        //   39: aload_3
        //   40: iconst_0
        //   41: invokeinterface 43 5 0
        //   46: pop
        //   47: aload_3
        //   48: invokevirtual 46	android/os/Parcel:readException	()V
        //   51: aload_3
        //   52: invokevirtual 50	android/os/Parcel:readInt	()I
        //   55: istore 7
        //   57: iconst_0
        //   58: istore 8
        //   60: iload 7
        //   62: ifeq +6 -> 68
        //   65: iconst_1
        //   66: istore 8
        //   68: aload_3
        //   69: invokevirtual 53	android/os/Parcel:recycle	()V
        //   72: aload_2
        //   73: invokevirtual 53	android/os/Parcel:recycle	()V
        //   76: iload 8
        //   78: ireturn
        //   79: aconst_null
        //   80: astore 5
        //   82: goto -56 -> 26
        //   85: astore 4
        //   87: aload_3
        //   88: invokevirtual 53	android/os/Parcel:recycle	()V
        //   91: aload_2
        //   92: invokevirtual 53	android/os/Parcel:recycle	()V
        //   95: aload 4
        //   97: athrow
        // Local variable table:
        //   start	length	slot	name	signature
        //   0	98	0	this	a
        //   0	98	1	paramb	b
        //   3	89	2	localParcel1	Parcel
        //   7	81	3	localParcel2	Parcel
        //   85	11	4	localObject	Object
        //   24	57	5	localIBinder	IBinder
        //   55	6	7	i	int
        //   58	19	8	bool	boolean
        // Exception table:
        //   from	to	target	type
        //   8	14	85	finally
        //   18	26	85	finally
        //   26	57	85	finally
      }
      
      public IBinder asBinder()
      {
        return this.a;
      }
      
      /* Error */
      public LatLng getCenter()
        throws RemoteException
      {
        // Byte code:
        //   0: invokestatic 24	android/os/Parcel:obtain	()Landroid/os/Parcel;
        //   3: astore_1
        //   4: invokestatic 24	android/os/Parcel:obtain	()Landroid/os/Parcel;
        //   7: astore_2
        //   8: aload_1
        //   9: ldc 26
        //   11: invokevirtual 30	android/os/Parcel:writeInterfaceToken	(Ljava/lang/String;)V
        //   14: aload_0
        //   15: getfield 15	com/google/android/gms/maps/model/internal/b$a$a:a	Landroid/os/IBinder;
        //   18: iconst_4
        //   19: aload_1
        //   20: aload_2
        //   21: iconst_0
        //   22: invokeinterface 43 5 0
        //   27: pop
        //   28: aload_2
        //   29: invokevirtual 46	android/os/Parcel:readException	()V
        //   32: aload_2
        //   33: invokevirtual 50	android/os/Parcel:readInt	()I
        //   36: ifeq +27 -> 63
        //   39: getstatic 61	com/google/android/gms/maps/model/LatLng:CREATOR	Lcom/google/android/gms/maps/model/LatLngCreator;
        //   42: aload_2
        //   43: invokevirtual 67	com/google/android/gms/maps/model/LatLngCreator:createFromParcel	(Landroid/os/Parcel;)Lcom/google/android/gms/maps/model/LatLng;
        //   46: astore 6
        //   48: aload 6
        //   50: astore 5
        //   52: aload_2
        //   53: invokevirtual 53	android/os/Parcel:recycle	()V
        //   56: aload_1
        //   57: invokevirtual 53	android/os/Parcel:recycle	()V
        //   60: aload 5
        //   62: areturn
        //   63: aconst_null
        //   64: astore 5
        //   66: goto -14 -> 52
        //   69: astore_3
        //   70: aload_2
        //   71: invokevirtual 53	android/os/Parcel:recycle	()V
        //   74: aload_1
        //   75: invokevirtual 53	android/os/Parcel:recycle	()V
        //   78: aload_3
        //   79: athrow
        // Local variable table:
        //   start	length	slot	name	signature
        //   0	80	0	this	a
        //   3	72	1	localParcel1	Parcel
        //   7	64	2	localParcel2	Parcel
        //   69	10	3	localObject	Object
        //   50	15	5	localLatLng1	LatLng
        //   46	3	6	localLatLng2	LatLng
        // Exception table:
        //   from	to	target	type
        //   8	48	69	finally
      }
      
      public int getFillColor()
        throws RemoteException
      {
        Parcel localParcel1 = Parcel.obtain();
        Parcel localParcel2 = Parcel.obtain();
        try
        {
          localParcel1.writeInterfaceToken("com.google.android.gms.maps.model.internal.ICircleDelegate");
          this.a.transact(12, localParcel1, localParcel2, 0);
          localParcel2.readException();
          int i = localParcel2.readInt();
          return i;
        }
        finally
        {
          localParcel2.recycle();
          localParcel1.recycle();
        }
      }
      
      public String getId()
        throws RemoteException
      {
        Parcel localParcel1 = Parcel.obtain();
        Parcel localParcel2 = Parcel.obtain();
        try
        {
          localParcel1.writeInterfaceToken("com.google.android.gms.maps.model.internal.ICircleDelegate");
          this.a.transact(2, localParcel1, localParcel2, 0);
          localParcel2.readException();
          String str = localParcel2.readString();
          return str;
        }
        finally
        {
          localParcel2.recycle();
          localParcel1.recycle();
        }
      }
      
      public double getRadius()
        throws RemoteException
      {
        Parcel localParcel1 = Parcel.obtain();
        Parcel localParcel2 = Parcel.obtain();
        try
        {
          localParcel1.writeInterfaceToken("com.google.android.gms.maps.model.internal.ICircleDelegate");
          this.a.transact(6, localParcel1, localParcel2, 0);
          localParcel2.readException();
          double d = localParcel2.readDouble();
          return d;
        }
        finally
        {
          localParcel2.recycle();
          localParcel1.recycle();
        }
      }
      
      public int getStrokeColor()
        throws RemoteException
      {
        Parcel localParcel1 = Parcel.obtain();
        Parcel localParcel2 = Parcel.obtain();
        try
        {
          localParcel1.writeInterfaceToken("com.google.android.gms.maps.model.internal.ICircleDelegate");
          this.a.transact(10, localParcel1, localParcel2, 0);
          localParcel2.readException();
          int i = localParcel2.readInt();
          return i;
        }
        finally
        {
          localParcel2.recycle();
          localParcel1.recycle();
        }
      }
      
      public float getStrokeWidth()
        throws RemoteException
      {
        Parcel localParcel1 = Parcel.obtain();
        Parcel localParcel2 = Parcel.obtain();
        try
        {
          localParcel1.writeInterfaceToken("com.google.android.gms.maps.model.internal.ICircleDelegate");
          this.a.transact(8, localParcel1, localParcel2, 0);
          localParcel2.readException();
          float f = localParcel2.readFloat();
          return f;
        }
        finally
        {
          localParcel2.recycle();
          localParcel1.recycle();
        }
      }
      
      public float getZIndex()
        throws RemoteException
      {
        Parcel localParcel1 = Parcel.obtain();
        Parcel localParcel2 = Parcel.obtain();
        try
        {
          localParcel1.writeInterfaceToken("com.google.android.gms.maps.model.internal.ICircleDelegate");
          this.a.transact(14, localParcel1, localParcel2, 0);
          localParcel2.readException();
          float f = localParcel2.readFloat();
          return f;
        }
        finally
        {
          localParcel2.recycle();
          localParcel1.recycle();
        }
      }
      
      public int hashCodeRemote()
        throws RemoteException
      {
        Parcel localParcel1 = Parcel.obtain();
        Parcel localParcel2 = Parcel.obtain();
        try
        {
          localParcel1.writeInterfaceToken("com.google.android.gms.maps.model.internal.ICircleDelegate");
          this.a.transact(18, localParcel1, localParcel2, 0);
          localParcel2.readException();
          int i = localParcel2.readInt();
          return i;
        }
        finally
        {
          localParcel2.recycle();
          localParcel1.recycle();
        }
      }
      
      public boolean isVisible()
        throws RemoteException
      {
        Parcel localParcel1 = Parcel.obtain();
        Parcel localParcel2 = Parcel.obtain();
        try
        {
          localParcel1.writeInterfaceToken("com.google.android.gms.maps.model.internal.ICircleDelegate");
          this.a.transact(16, localParcel1, localParcel2, 0);
          localParcel2.readException();
          int i = localParcel2.readInt();
          boolean bool = false;
          if (i != 0) {
            bool = true;
          }
          return bool;
        }
        finally
        {
          localParcel2.recycle();
          localParcel1.recycle();
        }
      }
      
      public void remove()
        throws RemoteException
      {
        Parcel localParcel1 = Parcel.obtain();
        Parcel localParcel2 = Parcel.obtain();
        try
        {
          localParcel1.writeInterfaceToken("com.google.android.gms.maps.model.internal.ICircleDelegate");
          this.a.transact(1, localParcel1, localParcel2, 0);
          localParcel2.readException();
          return;
        }
        finally
        {
          localParcel2.recycle();
          localParcel1.recycle();
        }
      }
      
      /* Error */
      public void setCenter(LatLng paramLatLng)
        throws RemoteException
      {
        // Byte code:
        //   0: invokestatic 24	android/os/Parcel:obtain	()Landroid/os/Parcel;
        //   3: astore_2
        //   4: invokestatic 24	android/os/Parcel:obtain	()Landroid/os/Parcel;
        //   7: astore_3
        //   8: aload_2
        //   9: ldc 26
        //   11: invokevirtual 30	android/os/Parcel:writeInterfaceToken	(Ljava/lang/String;)V
        //   14: aload_1
        //   15: ifnull +41 -> 56
        //   18: aload_2
        //   19: iconst_1
        //   20: invokevirtual 95	android/os/Parcel:writeInt	(I)V
        //   23: aload_1
        //   24: aload_2
        //   25: iconst_0
        //   26: invokevirtual 99	com/google/android/gms/maps/model/LatLng:writeToParcel	(Landroid/os/Parcel;I)V
        //   29: aload_0
        //   30: getfield 15	com/google/android/gms/maps/model/internal/b$a$a:a	Landroid/os/IBinder;
        //   33: iconst_3
        //   34: aload_2
        //   35: aload_3
        //   36: iconst_0
        //   37: invokeinterface 43 5 0
        //   42: pop
        //   43: aload_3
        //   44: invokevirtual 46	android/os/Parcel:readException	()V
        //   47: aload_3
        //   48: invokevirtual 53	android/os/Parcel:recycle	()V
        //   51: aload_2
        //   52: invokevirtual 53	android/os/Parcel:recycle	()V
        //   55: return
        //   56: aload_2
        //   57: iconst_0
        //   58: invokevirtual 95	android/os/Parcel:writeInt	(I)V
        //   61: goto -32 -> 29
        //   64: astore 4
        //   66: aload_3
        //   67: invokevirtual 53	android/os/Parcel:recycle	()V
        //   70: aload_2
        //   71: invokevirtual 53	android/os/Parcel:recycle	()V
        //   74: aload 4
        //   76: athrow
        // Local variable table:
        //   start	length	slot	name	signature
        //   0	77	0	this	a
        //   0	77	1	paramLatLng	LatLng
        //   3	68	2	localParcel1	Parcel
        //   7	60	3	localParcel2	Parcel
        //   64	11	4	localObject	Object
        // Exception table:
        //   from	to	target	type
        //   8	14	64	finally
        //   18	29	64	finally
        //   29	47	64	finally
        //   56	61	64	finally
      }
      
      public void setFillColor(int paramInt)
        throws RemoteException
      {
        Parcel localParcel1 = Parcel.obtain();
        Parcel localParcel2 = Parcel.obtain();
        try
        {
          localParcel1.writeInterfaceToken("com.google.android.gms.maps.model.internal.ICircleDelegate");
          localParcel1.writeInt(paramInt);
          this.a.transact(11, localParcel1, localParcel2, 0);
          localParcel2.readException();
          return;
        }
        finally
        {
          localParcel2.recycle();
          localParcel1.recycle();
        }
      }
      
      public void setRadius(double paramDouble)
        throws RemoteException
      {
        Parcel localParcel1 = Parcel.obtain();
        Parcel localParcel2 = Parcel.obtain();
        try
        {
          localParcel1.writeInterfaceToken("com.google.android.gms.maps.model.internal.ICircleDelegate");
          localParcel1.writeDouble(paramDouble);
          this.a.transact(5, localParcel1, localParcel2, 0);
          localParcel2.readException();
          return;
        }
        finally
        {
          localParcel2.recycle();
          localParcel1.recycle();
        }
      }
      
      public void setStrokeColor(int paramInt)
        throws RemoteException
      {
        Parcel localParcel1 = Parcel.obtain();
        Parcel localParcel2 = Parcel.obtain();
        try
        {
          localParcel1.writeInterfaceToken("com.google.android.gms.maps.model.internal.ICircleDelegate");
          localParcel1.writeInt(paramInt);
          this.a.transact(9, localParcel1, localParcel2, 0);
          localParcel2.readException();
          return;
        }
        finally
        {
          localParcel2.recycle();
          localParcel1.recycle();
        }
      }
      
      public void setStrokeWidth(float paramFloat)
        throws RemoteException
      {
        Parcel localParcel1 = Parcel.obtain();
        Parcel localParcel2 = Parcel.obtain();
        try
        {
          localParcel1.writeInterfaceToken("com.google.android.gms.maps.model.internal.ICircleDelegate");
          localParcel1.writeFloat(paramFloat);
          this.a.transact(7, localParcel1, localParcel2, 0);
          localParcel2.readException();
          return;
        }
        finally
        {
          localParcel2.recycle();
          localParcel1.recycle();
        }
      }
      
      public void setVisible(boolean paramBoolean)
        throws RemoteException
      {
        Parcel localParcel1 = Parcel.obtain();
        Parcel localParcel2 = Parcel.obtain();
        try
        {
          localParcel1.writeInterfaceToken("com.google.android.gms.maps.model.internal.ICircleDelegate");
          int i = 0;
          if (paramBoolean) {
            i = 1;
          }
          localParcel1.writeInt(i);
          this.a.transact(15, localParcel1, localParcel2, 0);
          localParcel2.readException();
          return;
        }
        finally
        {
          localParcel2.recycle();
          localParcel1.recycle();
        }
      }
      
      public void setZIndex(float paramFloat)
        throws RemoteException
      {
        Parcel localParcel1 = Parcel.obtain();
        Parcel localParcel2 = Parcel.obtain();
        try
        {
          localParcel1.writeInterfaceToken("com.google.android.gms.maps.model.internal.ICircleDelegate");
          localParcel1.writeFloat(paramFloat);
          this.a.transact(13, localParcel1, localParcel2, 0);
          localParcel2.readException();
          return;
        }
        finally
        {
          localParcel2.recycle();
          localParcel1.recycle();
        }
      }
    }
  }
}


/* Location:              /root/Documents/wemo_apk/classes-dex2jar.jar!/com/google/android/gms/maps/model/internal/b.class
 * Java compiler version: 6 (50.0)
 * JD-Core Version:       0.7.1
 */