package com.google.android.gms.maps.model.internal;

import android.os.Binder;
import android.os.IBinder;
import android.os.IInterface;
import android.os.Parcel;
import android.os.RemoteException;
import com.google.android.gms.maps.model.LatLng;
import java.util.ArrayList;
import java.util.List;

public abstract interface e
  extends IInterface
{
  public abstract boolean a(e parame)
    throws RemoteException;
  
  public abstract int getFillColor()
    throws RemoteException;
  
  public abstract List getHoles()
    throws RemoteException;
  
  public abstract String getId()
    throws RemoteException;
  
  public abstract List<LatLng> getPoints()
    throws RemoteException;
  
  public abstract int getStrokeColor()
    throws RemoteException;
  
  public abstract float getStrokeWidth()
    throws RemoteException;
  
  public abstract float getZIndex()
    throws RemoteException;
  
  public abstract int hashCodeRemote()
    throws RemoteException;
  
  public abstract boolean isGeodesic()
    throws RemoteException;
  
  public abstract boolean isVisible()
    throws RemoteException;
  
  public abstract void remove()
    throws RemoteException;
  
  public abstract void setFillColor(int paramInt)
    throws RemoteException;
  
  public abstract void setGeodesic(boolean paramBoolean)
    throws RemoteException;
  
  public abstract void setHoles(List paramList)
    throws RemoteException;
  
  public abstract void setPoints(List<LatLng> paramList)
    throws RemoteException;
  
  public abstract void setStrokeColor(int paramInt)
    throws RemoteException;
  
  public abstract void setStrokeWidth(float paramFloat)
    throws RemoteException;
  
  public abstract void setVisible(boolean paramBoolean)
    throws RemoteException;
  
  public abstract void setZIndex(float paramFloat)
    throws RemoteException;
  
  public static abstract class a
    extends Binder
    implements e
  {
    public static e R(IBinder paramIBinder)
    {
      if (paramIBinder == null) {
        return null;
      }
      IInterface localIInterface = paramIBinder.queryLocalInterface("com.google.android.gms.maps.model.internal.IPolygonDelegate");
      if ((localIInterface != null) && ((localIInterface instanceof e))) {
        return (e)localIInterface;
      }
      return new a(paramIBinder);
    }
    
    public boolean onTransact(int paramInt1, Parcel paramParcel1, Parcel paramParcel2, int paramInt2)
      throws RemoteException
    {
      switch (paramInt1)
      {
      default: 
        return super.onTransact(paramInt1, paramParcel1, paramParcel2, paramInt2);
      case 1598968902: 
        paramParcel2.writeString("com.google.android.gms.maps.model.internal.IPolygonDelegate");
        return true;
      case 1: 
        paramParcel1.enforceInterface("com.google.android.gms.maps.model.internal.IPolygonDelegate");
        remove();
        paramParcel2.writeNoException();
        return true;
      case 2: 
        paramParcel1.enforceInterface("com.google.android.gms.maps.model.internal.IPolygonDelegate");
        String str = getId();
        paramParcel2.writeNoException();
        paramParcel2.writeString(str);
        return true;
      case 3: 
        paramParcel1.enforceInterface("com.google.android.gms.maps.model.internal.IPolygonDelegate");
        setPoints(paramParcel1.createTypedArrayList(LatLng.CREATOR));
        paramParcel2.writeNoException();
        return true;
      case 4: 
        paramParcel1.enforceInterface("com.google.android.gms.maps.model.internal.IPolygonDelegate");
        List localList2 = getPoints();
        paramParcel2.writeNoException();
        paramParcel2.writeTypedList(localList2);
        return true;
      case 5: 
        paramParcel1.enforceInterface("com.google.android.gms.maps.model.internal.IPolygonDelegate");
        setHoles(paramParcel1.readArrayList(getClass().getClassLoader()));
        paramParcel2.writeNoException();
        return true;
      case 6: 
        paramParcel1.enforceInterface("com.google.android.gms.maps.model.internal.IPolygonDelegate");
        List localList1 = getHoles();
        paramParcel2.writeNoException();
        paramParcel2.writeList(localList1);
        return true;
      case 7: 
        paramParcel1.enforceInterface("com.google.android.gms.maps.model.internal.IPolygonDelegate");
        setStrokeWidth(paramParcel1.readFloat());
        paramParcel2.writeNoException();
        return true;
      case 8: 
        paramParcel1.enforceInterface("com.google.android.gms.maps.model.internal.IPolygonDelegate");
        float f2 = getStrokeWidth();
        paramParcel2.writeNoException();
        paramParcel2.writeFloat(f2);
        return true;
      case 9: 
        paramParcel1.enforceInterface("com.google.android.gms.maps.model.internal.IPolygonDelegate");
        setStrokeColor(paramParcel1.readInt());
        paramParcel2.writeNoException();
        return true;
      case 10: 
        paramParcel1.enforceInterface("com.google.android.gms.maps.model.internal.IPolygonDelegate");
        int i3 = getStrokeColor();
        paramParcel2.writeNoException();
        paramParcel2.writeInt(i3);
        return true;
      case 11: 
        paramParcel1.enforceInterface("com.google.android.gms.maps.model.internal.IPolygonDelegate");
        setFillColor(paramParcel1.readInt());
        paramParcel2.writeNoException();
        return true;
      case 12: 
        paramParcel1.enforceInterface("com.google.android.gms.maps.model.internal.IPolygonDelegate");
        int i2 = getFillColor();
        paramParcel2.writeNoException();
        paramParcel2.writeInt(i2);
        return true;
      case 13: 
        paramParcel1.enforceInterface("com.google.android.gms.maps.model.internal.IPolygonDelegate");
        setZIndex(paramParcel1.readFloat());
        paramParcel2.writeNoException();
        return true;
      case 14: 
        paramParcel1.enforceInterface("com.google.android.gms.maps.model.internal.IPolygonDelegate");
        float f1 = getZIndex();
        paramParcel2.writeNoException();
        paramParcel2.writeFloat(f1);
        return true;
      case 15: 
        paramParcel1.enforceInterface("com.google.android.gms.maps.model.internal.IPolygonDelegate");
        int i1 = paramParcel1.readInt();
        boolean bool5 = false;
        if (i1 != 0) {
          bool5 = true;
        }
        setVisible(bool5);
        paramParcel2.writeNoException();
        return true;
      case 16: 
        paramParcel1.enforceInterface("com.google.android.gms.maps.model.internal.IPolygonDelegate");
        boolean bool4 = isVisible();
        paramParcel2.writeNoException();
        int n = 0;
        if (bool4) {
          n = 1;
        }
        paramParcel2.writeInt(n);
        return true;
      case 17: 
        paramParcel1.enforceInterface("com.google.android.gms.maps.model.internal.IPolygonDelegate");
        int m = paramParcel1.readInt();
        boolean bool3 = false;
        if (m != 0) {
          bool3 = true;
        }
        setGeodesic(bool3);
        paramParcel2.writeNoException();
        return true;
      case 18: 
        paramParcel1.enforceInterface("com.google.android.gms.maps.model.internal.IPolygonDelegate");
        boolean bool2 = isGeodesic();
        paramParcel2.writeNoException();
        int k = 0;
        if (bool2) {
          k = 1;
        }
        paramParcel2.writeInt(k);
        return true;
      case 19: 
        paramParcel1.enforceInterface("com.google.android.gms.maps.model.internal.IPolygonDelegate");
        boolean bool1 = a(R(paramParcel1.readStrongBinder()));
        paramParcel2.writeNoException();
        int j = 0;
        if (bool1) {
          j = 1;
        }
        paramParcel2.writeInt(j);
        return true;
      }
      paramParcel1.enforceInterface("com.google.android.gms.maps.model.internal.IPolygonDelegate");
      int i = hashCodeRemote();
      paramParcel2.writeNoException();
      paramParcel2.writeInt(i);
      return true;
    }
    
    private static class a
      implements e
    {
      private IBinder a;
      
      a(IBinder paramIBinder)
      {
        this.a = paramIBinder;
      }
      
      /* Error */
      public boolean a(e parame)
        throws RemoteException
      {
        // Byte code:
        //   0: invokestatic 24	android/os/Parcel:obtain	()Landroid/os/Parcel;
        //   3: astore_2
        //   4: invokestatic 24	android/os/Parcel:obtain	()Landroid/os/Parcel;
        //   7: astore_3
        //   8: aload_2
        //   9: ldc 26
        //   11: invokevirtual 30	android/os/Parcel:writeInterfaceToken	(Ljava/lang/String;)V
        //   14: aload_1
        //   15: ifnull +64 -> 79
        //   18: aload_1
        //   19: invokeinterface 34 1 0
        //   24: astore 5
        //   26: aload_2
        //   27: aload 5
        //   29: invokevirtual 37	android/os/Parcel:writeStrongBinder	(Landroid/os/IBinder;)V
        //   32: aload_0
        //   33: getfield 15	com/google/android/gms/maps/model/internal/e$a$a:a	Landroid/os/IBinder;
        //   36: bipush 19
        //   38: aload_2
        //   39: aload_3
        //   40: iconst_0
        //   41: invokeinterface 43 5 0
        //   46: pop
        //   47: aload_3
        //   48: invokevirtual 46	android/os/Parcel:readException	()V
        //   51: aload_3
        //   52: invokevirtual 50	android/os/Parcel:readInt	()I
        //   55: istore 7
        //   57: iconst_0
        //   58: istore 8
        //   60: iload 7
        //   62: ifeq +6 -> 68
        //   65: iconst_1
        //   66: istore 8
        //   68: aload_3
        //   69: invokevirtual 53	android/os/Parcel:recycle	()V
        //   72: aload_2
        //   73: invokevirtual 53	android/os/Parcel:recycle	()V
        //   76: iload 8
        //   78: ireturn
        //   79: aconst_null
        //   80: astore 5
        //   82: goto -56 -> 26
        //   85: astore 4
        //   87: aload_3
        //   88: invokevirtual 53	android/os/Parcel:recycle	()V
        //   91: aload_2
        //   92: invokevirtual 53	android/os/Parcel:recycle	()V
        //   95: aload 4
        //   97: athrow
        // Local variable table:
        //   start	length	slot	name	signature
        //   0	98	0	this	a
        //   0	98	1	parame	e
        //   3	89	2	localParcel1	Parcel
        //   7	81	3	localParcel2	Parcel
        //   85	11	4	localObject	Object
        //   24	57	5	localIBinder	IBinder
        //   55	6	7	i	int
        //   58	19	8	bool	boolean
        // Exception table:
        //   from	to	target	type
        //   8	14	85	finally
        //   18	26	85	finally
        //   26	57	85	finally
      }
      
      public IBinder asBinder()
      {
        return this.a;
      }
      
      public int getFillColor()
        throws RemoteException
      {
        Parcel localParcel1 = Parcel.obtain();
        Parcel localParcel2 = Parcel.obtain();
        try
        {
          localParcel1.writeInterfaceToken("com.google.android.gms.maps.model.internal.IPolygonDelegate");
          this.a.transact(12, localParcel1, localParcel2, 0);
          localParcel2.readException();
          int i = localParcel2.readInt();
          return i;
        }
        finally
        {
          localParcel2.recycle();
          localParcel1.recycle();
        }
      }
      
      public List getHoles()
        throws RemoteException
      {
        Parcel localParcel1 = Parcel.obtain();
        Parcel localParcel2 = Parcel.obtain();
        try
        {
          localParcel1.writeInterfaceToken("com.google.android.gms.maps.model.internal.IPolygonDelegate");
          this.a.transact(6, localParcel1, localParcel2, 0);
          localParcel2.readException();
          ArrayList localArrayList = localParcel2.readArrayList(getClass().getClassLoader());
          return localArrayList;
        }
        finally
        {
          localParcel2.recycle();
          localParcel1.recycle();
        }
      }
      
      public String getId()
        throws RemoteException
      {
        Parcel localParcel1 = Parcel.obtain();
        Parcel localParcel2 = Parcel.obtain();
        try
        {
          localParcel1.writeInterfaceToken("com.google.android.gms.maps.model.internal.IPolygonDelegate");
          this.a.transact(2, localParcel1, localParcel2, 0);
          localParcel2.readException();
          String str = localParcel2.readString();
          return str;
        }
        finally
        {
          localParcel2.recycle();
          localParcel1.recycle();
        }
      }
      
      public List<LatLng> getPoints()
        throws RemoteException
      {
        Parcel localParcel1 = Parcel.obtain();
        Parcel localParcel2 = Parcel.obtain();
        try
        {
          localParcel1.writeInterfaceToken("com.google.android.gms.maps.model.internal.IPolygonDelegate");
          this.a.transact(4, localParcel1, localParcel2, 0);
          localParcel2.readException();
          ArrayList localArrayList = localParcel2.createTypedArrayList(LatLng.CREATOR);
          return localArrayList;
        }
        finally
        {
          localParcel2.recycle();
          localParcel1.recycle();
        }
      }
      
      public int getStrokeColor()
        throws RemoteException
      {
        Parcel localParcel1 = Parcel.obtain();
        Parcel localParcel2 = Parcel.obtain();
        try
        {
          localParcel1.writeInterfaceToken("com.google.android.gms.maps.model.internal.IPolygonDelegate");
          this.a.transact(10, localParcel1, localParcel2, 0);
          localParcel2.readException();
          int i = localParcel2.readInt();
          return i;
        }
        finally
        {
          localParcel2.recycle();
          localParcel1.recycle();
        }
      }
      
      public float getStrokeWidth()
        throws RemoteException
      {
        Parcel localParcel1 = Parcel.obtain();
        Parcel localParcel2 = Parcel.obtain();
        try
        {
          localParcel1.writeInterfaceToken("com.google.android.gms.maps.model.internal.IPolygonDelegate");
          this.a.transact(8, localParcel1, localParcel2, 0);
          localParcel2.readException();
          float f = localParcel2.readFloat();
          return f;
        }
        finally
        {
          localParcel2.recycle();
          localParcel1.recycle();
        }
      }
      
      public float getZIndex()
        throws RemoteException
      {
        Parcel localParcel1 = Parcel.obtain();
        Parcel localParcel2 = Parcel.obtain();
        try
        {
          localParcel1.writeInterfaceToken("com.google.android.gms.maps.model.internal.IPolygonDelegate");
          this.a.transact(14, localParcel1, localParcel2, 0);
          localParcel2.readException();
          float f = localParcel2.readFloat();
          return f;
        }
        finally
        {
          localParcel2.recycle();
          localParcel1.recycle();
        }
      }
      
      public int hashCodeRemote()
        throws RemoteException
      {
        Parcel localParcel1 = Parcel.obtain();
        Parcel localParcel2 = Parcel.obtain();
        try
        {
          localParcel1.writeInterfaceToken("com.google.android.gms.maps.model.internal.IPolygonDelegate");
          this.a.transact(20, localParcel1, localParcel2, 0);
          localParcel2.readException();
          int i = localParcel2.readInt();
          return i;
        }
        finally
        {
          localParcel2.recycle();
          localParcel1.recycle();
        }
      }
      
      public boolean isGeodesic()
        throws RemoteException
      {
        Parcel localParcel1 = Parcel.obtain();
        Parcel localParcel2 = Parcel.obtain();
        try
        {
          localParcel1.writeInterfaceToken("com.google.android.gms.maps.model.internal.IPolygonDelegate");
          this.a.transact(18, localParcel1, localParcel2, 0);
          localParcel2.readException();
          int i = localParcel2.readInt();
          boolean bool = false;
          if (i != 0) {
            bool = true;
          }
          return bool;
        }
        finally
        {
          localParcel2.recycle();
          localParcel1.recycle();
        }
      }
      
      public boolean isVisible()
        throws RemoteException
      {
        Parcel localParcel1 = Parcel.obtain();
        Parcel localParcel2 = Parcel.obtain();
        try
        {
          localParcel1.writeInterfaceToken("com.google.android.gms.maps.model.internal.IPolygonDelegate");
          this.a.transact(16, localParcel1, localParcel2, 0);
          localParcel2.readException();
          int i = localParcel2.readInt();
          boolean bool = false;
          if (i != 0) {
            bool = true;
          }
          return bool;
        }
        finally
        {
          localParcel2.recycle();
          localParcel1.recycle();
        }
      }
      
      public void remove()
        throws RemoteException
      {
        Parcel localParcel1 = Parcel.obtain();
        Parcel localParcel2 = Parcel.obtain();
        try
        {
          localParcel1.writeInterfaceToken("com.google.android.gms.maps.model.internal.IPolygonDelegate");
          this.a.transact(1, localParcel1, localParcel2, 0);
          localParcel2.readException();
          return;
        }
        finally
        {
          localParcel2.recycle();
          localParcel1.recycle();
        }
      }
      
      public void setFillColor(int paramInt)
        throws RemoteException
      {
        Parcel localParcel1 = Parcel.obtain();
        Parcel localParcel2 = Parcel.obtain();
        try
        {
          localParcel1.writeInterfaceToken("com.google.android.gms.maps.model.internal.IPolygonDelegate");
          localParcel1.writeInt(paramInt);
          this.a.transact(11, localParcel1, localParcel2, 0);
          localParcel2.readException();
          return;
        }
        finally
        {
          localParcel2.recycle();
          localParcel1.recycle();
        }
      }
      
      public void setGeodesic(boolean paramBoolean)
        throws RemoteException
      {
        Parcel localParcel1 = Parcel.obtain();
        Parcel localParcel2 = Parcel.obtain();
        try
        {
          localParcel1.writeInterfaceToken("com.google.android.gms.maps.model.internal.IPolygonDelegate");
          int i = 0;
          if (paramBoolean) {
            i = 1;
          }
          localParcel1.writeInt(i);
          this.a.transact(17, localParcel1, localParcel2, 0);
          localParcel2.readException();
          return;
        }
        finally
        {
          localParcel2.recycle();
          localParcel1.recycle();
        }
      }
      
      public void setHoles(List paramList)
        throws RemoteException
      {
        Parcel localParcel1 = Parcel.obtain();
        Parcel localParcel2 = Parcel.obtain();
        try
        {
          localParcel1.writeInterfaceToken("com.google.android.gms.maps.model.internal.IPolygonDelegate");
          localParcel1.writeList(paramList);
          this.a.transact(5, localParcel1, localParcel2, 0);
          localParcel2.readException();
          return;
        }
        finally
        {
          localParcel2.recycle();
          localParcel1.recycle();
        }
      }
      
      public void setPoints(List<LatLng> paramList)
        throws RemoteException
      {
        Parcel localParcel1 = Parcel.obtain();
        Parcel localParcel2 = Parcel.obtain();
        try
        {
          localParcel1.writeInterfaceToken("com.google.android.gms.maps.model.internal.IPolygonDelegate");
          localParcel1.writeTypedList(paramList);
          this.a.transact(3, localParcel1, localParcel2, 0);
          localParcel2.readException();
          return;
        }
        finally
        {
          localParcel2.recycle();
          localParcel1.recycle();
        }
      }
      
      public void setStrokeColor(int paramInt)
        throws RemoteException
      {
        Parcel localParcel1 = Parcel.obtain();
        Parcel localParcel2 = Parcel.obtain();
        try
        {
          localParcel1.writeInterfaceToken("com.google.android.gms.maps.model.internal.IPolygonDelegate");
          localParcel1.writeInt(paramInt);
          this.a.transact(9, localParcel1, localParcel2, 0);
          localParcel2.readException();
          return;
        }
        finally
        {
          localParcel2.recycle();
          localParcel1.recycle();
        }
      }
      
      public void setStrokeWidth(float paramFloat)
        throws RemoteException
      {
        Parcel localParcel1 = Parcel.obtain();
        Parcel localParcel2 = Parcel.obtain();
        try
        {
          localParcel1.writeInterfaceToken("com.google.android.gms.maps.model.internal.IPolygonDelegate");
          localParcel1.writeFloat(paramFloat);
          this.a.transact(7, localParcel1, localParcel2, 0);
          localParcel2.readException();
          return;
        }
        finally
        {
          localParcel2.recycle();
          localParcel1.recycle();
        }
      }
      
      public void setVisible(boolean paramBoolean)
        throws RemoteException
      {
        Parcel localParcel1 = Parcel.obtain();
        Parcel localParcel2 = Parcel.obtain();
        try
        {
          localParcel1.writeInterfaceToken("com.google.android.gms.maps.model.internal.IPolygonDelegate");
          int i = 0;
          if (paramBoolean) {
            i = 1;
          }
          localParcel1.writeInt(i);
          this.a.transact(15, localParcel1, localParcel2, 0);
          localParcel2.readException();
          return;
        }
        finally
        {
          localParcel2.recycle();
          localParcel1.recycle();
        }
      }
      
      public void setZIndex(float paramFloat)
        throws RemoteException
      {
        Parcel localParcel1 = Parcel.obtain();
        Parcel localParcel2 = Parcel.obtain();
        try
        {
          localParcel1.writeInterfaceToken("com.google.android.gms.maps.model.internal.IPolygonDelegate");
          localParcel1.writeFloat(paramFloat);
          this.a.transact(13, localParcel1, localParcel2, 0);
          localParcel2.readException();
          return;
        }
        finally
        {
          localParcel2.recycle();
          localParcel1.recycle();
        }
      }
    }
  }
}


/* Location:              /root/Documents/wemo_apk/classes-dex2jar.jar!/com/google/android/gms/maps/model/internal/e.class
 * Java compiler version: 6 (50.0)
 * JD-Core Version:       0.7.1
 */